Workbook

Sheet Sheet1
A1: Annexure | B1: Budgeted cost | C1: Actual Cost | D1: Remaining Cost
A2: Annexure I | B2: =Summary!C9 -> 179850 | C2: =Summary!E9 -> 0 | D2: =B2-C2 -> 179850
A3: Annexure II | B3: =Summary!C12 -> 36193 | C3: =Summary!E12 -> 20621.784 | D3: =B3-C3 -> 15571.216
A4: Annexure III | B4: =Summary!C15 -> 936075 | C4: =Summary!E15 -> 886356.69 | D4: =B4-C4 -> 49718.31
A5: Annexure IV | B5: =Summary!C18 -> 275000 | C5: =Summary!E18 -> 127321 | D5: =B5-C5 -> 147679
A6: Annexure V | B6: =Summary!C21 -> 917500 | C6: =Summary!E21 -> 692348 | D6: =B6-C6 -> 225152
A7: Annexure VI | B7: =Summary!C24 -> 6475383.6 | C7: =Summary!E24 -> 6527134 | D7: =B7-C7 -> -51750.472
A8: Annexure VII | B8: =Summary!C27 -> 1760997 | C8: =Summary!E27 -> 1534282.4 | D8: =B8-C8 -> 226714.6
A9: Annexure VIII | B9: =Summary!C30 -> 1320000 | C9: =Summary!E30 -> 712385.22 | D9: =B9-C9 -> 607614.78
A10: Annexure IX | B10: =Summary!C33 -> 1856500 | C10: =Summary!E33 -> 1107431.5 | D10: =B10-C10 -> 749068.54
A11: Annexure X | B11: =Summary!C35 -> 4946840 | C11: =Summary!E35 -> 3498986.6 | D11: =B11-C11 -> 1447853.4
A12: Annexure XI | B12: =Summary!C37 -> 257150 | C12: =Summary!E37 -> 64492.822 | D12: =B12-C12 -> 192657.18
A13: T
C20: Total budgeted Cost | D20: Total Actual Cost | E20: Remaining Cost
C21: =SUM(B2:B12) -> 18961489 | D21: =SUM(C2:C12) -> 15171360 | E21: =C21-D21 -> 3790128.5
C40: Major Drilling Eq | D40: Cost
C41: Top Drive | D41: ='Ann VI-Drill'!N7 -> 687875.43
C42: Iron Rouchneck | D42: ='Ann VI-Drill'!N16 -> 738836.46
C43: Draw-works | D43: =SUM('Ann VI-Drill'!N11:N12) -> 999624
C44: Mud pumps | D44: ='Ann VI-Drill'!N15 -> 607787
C45: Crown block | D45: ='Ann VI-Drill'!N5 -> 97058.98
C46: Travelling Block | D46: ='Ann VI-Drill'!N9 -> 143156
C47: Rotary Table | D47: ='Ann VI-Drill'!N14 -> 127166.3
C48: Deadline Anchor | D48: ='Ann VI-Drill'!N10 -> 11282
C49: BOP | D49: =SUM('Ann VI-Drill'!N18:N19) -> 1363788
C50: Diverter | D50: ='Ann VI-Drill'!N17 -> 415300.7
C51: Manifold | D51: ='Ann VI-Drill'!N30 -> 387579.24
D52: =SUM(D41:D51) -> 5579454.1

Sheet Dashboard

Sheet Summary
A1: BUDGETED VS ACTUAL EXPENSES FOR JINDAL PIONEER RECERTIFICATION & MISCELLANEOUS SERVICES SUMMARY SHEET 17-03-2026
B2: SHIPYARD | G2: 1 | H2: 87
A3: Sr. No. | B3: Description | C3: Budgetory Cost | D3: Budgetory cost | E3: Actual Cost | F3: Remaining Cost
C4: (in USD) | D4: (in INR) | E4: (USD) | F4: (USD) | H4: Annexure Ref
A6: A | B6: ='Ann I'!C2 -> TOWAGE EXPENSES
A7: I | B7: Marine Warranty Surveyor ( Lamprell to Khalid Port) | C7: ='Ann I'!C12 -> 15650 | D7: =C7*H2 -> 1361550 | E7: ='Ann I'!E12 -> 0 | F7: ='Ann I'!F12 -> 15650 | H7: ='[1]Annexure I'!G2 -> Annexure I
A8: II | B8: TOW BOAT AND OTHER EXPENSES | C8: ='Ann I'!C22 -> 164200 | D8: =C8*H2 -> 14285400 | E8: ='Ann I'!E23 -> 0 | F8: ='Ann I'!F22 -> 164200
B9: Total | C9: =SUM(C7:C8) -> 179850 | D9: =SUM(D7:D8) -> 15646950 | E9: =SUM(E7:E8) -> 0 | F9: =SUM(F7:F8) -> 179850
A10: B | B10: ='Ann II'!B2:E2 -> CLASS RELATED EXPENSES
A11: I | B11: CLASS SURVEY AND RELATED EXPENSES | C11: ='Ann II'!C10 -> 36193 | D11: =C11*87 -> 3148791 | E11: ='Ann II'!I10 -> 20621.784 | F11: ='Ann II'!J10 -> 15571.216 | H11: ='[1]Annexure II '!G2 -> Annexure II
B12: Total | C12: =SUM(C11:C11) -> 36193 | D12: =SUM(D11:D11) -> 3148791 | E12: ='Ann II'!I10 -> 20621.784 | F12: ='Ann II'!J10 -> 15571.216
A13: C | B13: ='Ann III'!B2:R2 -> KHALID AND LAMPRELL PORT EXPENSES
A14: i | B14: Berthing Charges, fuel, water & Other Related Works | C14: ='Ann III'!H18 -> 936075 | D14: =C14*87 -> 81438525 | E14: ='Ann III'!N18 -> 886356.69 | F14: ='Ann III'!O18 -> 151718.31 | H14: Annexure III
B15: Total | C15: =C14 -> 936075 | D15: =SUM(D14:D14) -> 81438525 | E15: ='Ann III'!N18 -> 886356.69 | F15: ='Ann III'!O18 -> 151718.31
A16: ='[1]Annexure IV '!A6 -> D | B16: Clearing Forwarding and Custom Duty Charges
A17: i | B17: Clearing, Forwarding charges Customs Duty charges etc. | C17: ='Ann IV'!C10 -> 275000 | D17: =C17*87 -> 23925000 | E17: ='Ann IV'!E10 -> 127321 | F17: ='Ann IV'!F10 -> 147679 | H17: ='[1]Annexure IV '!G2 -> Annexure IV
B18: Total | C18: =SUM(C17:C17) -> 275000 | D18: =SUM(D17:D17) -> 23925000 | E18: ='Ann IV'!E10 -> 127321 | F18: ='Ann IV'!F10 -> 147679
A19: E | B19: ='[1]Annexure V'!B6:E6 -> Crew Expenses
A20: i | B20: Crew flights, visa, CDC, Catering, Communication, Salary | C20: ='Ann V'!C12 -> 917500 | D20: =C20*87 -> 79822500 | E20: ='Ann V'!E12 -> 692348 | F20: ='Ann V'!F12 -> 225152 | H20: ='[1]Annexure V'!G2 -> Annexure V
B21: Total | C21: =SUM(C20:C20) -> 917500 | D21: =SUM(D20:D20) -> 79822500 | E21: ='Ann V'!E12 -> 692348 | F21: ='Ann V'!F12 -> 225152
A22: F | B22: Drilling, Well Control and Solid Control
A23: i | B23: Work to be done - Drilling | C23: ='Ann VI-Drill'!F62 -> 6475383.6 | D23: =C23*87 -> 5.6335837e+08 | E23: ='Ann VI-Drill'!N62 -> 6527134 | F23: ='Ann VI-Drill'!O62 -> -51750.472 | H23: ='[1]An VI - Drill'!K2 -> Annexure VI
B24: Total | C24: =SUM(C23:C23) -> 6475383.6 | D24: =SUM(D23:D23) -> 5.6335837e+08 | E24: ='Ann VI-Drill'!N62 -> 6527134 | F24: ='Ann VI-Drill'!O62 -> -51750.472
A25: G | B25: Mechanical
B26: Work to be done - Mechanical | C26: ='Ann VII-Mech'!F33 -> 1760997 | D26: =C26*H2 -> 153206739 | E26: ='Ann VII-Mech'!M33 -> 1534282.4 | F26: ='Ann VII-Mech'!N33 -> 226714.6 | H26: ='[1]An VII - Mech'!K2 -> Annexure VII
B27: Total | C27: {=C26:D26} -> 1760997 | D27: 153206739 | E27: ='Ann VII-Mech'!M33 -> 1534282.4 | F27: ='Ann VII-Mech'!N33 -> 226714.6
A28: H | B28: Electrical and Power Plant
A29: i | B29: Work to be done - Electircal,power | C29: ='Ann VIII-Elec'!F41 -> 1320000 | D29: =C29*H2 -> 114840000 | E29: ='Ann VIII-Elec'!N41 -> 712385.22 | F29: ='Ann VIII-Elec'!O41 -> 607614.78 | H29: ='[1]An VIII -Elec'!K2 -> Annexure VIII
B30: Total | C30: =SUM(C29:C29) -> 1320000 | D30: =D29 -> 114840000 | E30: ='Ann VIII-Elec'!N41 -> 712385.22 | F30: ='Ann VIII-Elec'!O41 -> 607614.78
A31: I | B31: Lifting gear, Marine and Safety
A32: i | B32: Work to be done - Marine and Safety | C32: ='Ann IX-Marine'!F66 -> 1856500 | D32: =C32*87 -> 161515500 | E32: ='Ann IX-Marine'!N66 -> 1107431.5 | F32: ='Ann IX-Marine'!O66 -> 749068.54 | H32: ='[1]An IX - Marine'!K2 -> Annexure IX
B33: Total | C33: =SUM(C32:C32) -> 1856500 | D33: =D32 -> 161515500 | E33: ='Ann IX-Marine'!N66 -> 1107431.5 | F33: ='Ann IX-Marine'!O66 -> 749068.54
A34: J | B34: Additional Items/ Shortfall as per ONGC tender | H34: Annexure X
B35: Total | C35: ='Ann X-Contractual Req'!C49 -> 4946840 | D35: =C35*87 -> 430375080 | E35: ='Ann X-Contractual Req'!J49 -> 3498986.6 | F35: ='Ann X-Contractual Req'!K49 -> 1447853.4
A36: K | B36: Missing items from rig Jindal Pioneer -post handover from Saipem | H36: Annexure XI
B37: Total | C37: ='Ann XI-Missing items Saipem'!C20 -> 257150 | D37: =C37*87 -> 22372050 | E37: ='Ann XI-Missing items Saipem'!H20 -> 64492.822 | F37: ='Ann XI-Missing items Saipem'!I20 -> 192657.18 | H37: Not included in Total
A38: TOTAL | C38: =SUM(C9+C12+C15+C18+C21+C24+C27+C30+C33+C35+C37) -> 18961489 | D38: =SUM(D9+D12+D15+D18+D21+D24+D27+D30+D33+D35+D37) -> 1.6496495e+09 | E38: =E9+E12+E15+E18+E21+E24+E27+E30+E33+E35+E37 -> 15171360 | F38: =F9+F12+F15+F18+F21+F24+F27+F30+F33+F35 -> 3699471.3
A40: TOTAL (IN USD MILLION) (Annex I to X) | C40: =C38/1000000 -> 18.961489 | E40: =E38/1000000 -> 15.17136 | F40: =F38/1000000 -> 3.6994713

Sheet Ann I
A1: BUDGETED EXPENSES FOR JINDAL PIONEER RECERTIFICATION & MISCELLANEOUS SERVICES -ANNEXURE I
A2: A | C2: TOWAGE EXPENSES
A3: Sr. No. | B3: Description | C3: Budgetory Cost | D3: Budgetory Cost | E3: Actual Cost | F3: Surplus/Exceeded | G3: Remarks
C4: (in USD) | D4: (in INR) | E4: (in USD) | F4: (in USD)
A7: I | C7: Marine Warranty Surveyor ( Lamprell to Khalid Port to India)
A8: 1 | B8: Location Certifcate Approval | C8: =1925*2 -> 3850 | D8: =C8*87 -> 334950 | E8: 0 | F8: =C8-E8 -> 3850 | G8: Considering Location Approval at Port Khalid and India 1925$ per approval
A9: 2 | B9: Towage Certificate Approval | C9: =900*2 -> 1800 | D9: =C9*87 -> 156600 | E9: 0 | F9: =C9-E9 -> 1800 | G9: 900$ per approval (2 considered)
A10: 3 | B10: Other miscellaneous charges towards flight tickets, transportation etc. of MWS | C10: 2000 | D10: =C10*87 -> 174000 | E10: 0 | F10: =C10-E10 -> 2000
A11: 4 | B11: Day Rate of Onboard Surveyor(Rig Mover/MWS) | C11: =2000*4 -> 8000 | D11: =C11*87 -> 696000 | E11: 0 | F11: =C11-E11 -> 8000 | G11: Considered for 4 days Rig move from Hamriyah to port Khalid
A12: Total | C12: =SUM(C8:C11) -> 15650 | D12: =SUM(D8:D11) -> 1361550 | E12: =SUM(E8:E11) -> 0 | F12: =SUM(F8:F11) -> 15650
A13: II | C13: Tow Boat & other Port Expenses
A14: 6 | B14: Sea Bed Survey(Khalid Port) | C14: 4000 | D14: =C14*87 -> 348000 | E14: 0 | F14: =C14-E14 -> 4000 | G14: Considered 1 Sea bed surveys (one in port khalid)
A15: 7 | B15: Marine Weather Forecast | C15: =50*4 -> 200 | D15: =C15*87 -> 17400 | E15: 0 | F15: =C15-E15 -> 200 | G15: Considered for 4 days Rig move from Hamriyah to port Khalid
A16: 8 | B16: Tow Boat Charges -Lamprell to port khalid | C16: 150000 | D16: =C16*87 -> 13050000 | E16: 0 | F16: =C16-E16 -> 150000 | G16: Includes SR NO (9,10,11,12)
A17: 9 | B17: Inward & Outward Port Clearance for Rig | D17: =C17*87 -> 0 | E17: 0 | F17: =C17-E17 -> 0
A18: 10 | B18: Inward & Outward Port Clearance for Tug | D18: =C18*87 -> 0 | E18: 0 | F18: =C18-E18 -> 0
A19: 11 | B19: Pilot Charges | D19: =C19*87 -> 0 | E19: 0 | F19: =C19-E19 -> 0
A20: 12 | B20: Diesel Consumption while Rig Tow | D20: =C20*87 -> 0 | E20: 0 | F20: =C20-E20 -> 0
A21: 13 | B21: Contiengency & other misc charges | C21: 10000 | D21: =C21*87 -> 870000 | E21: 0 | F21: =C21-E21 -> 10000
C22: =SUM(C14:C21) -> 164200 | D22: =C22*87 -> 14285400 | E22: 0 | F22: =C22-E22 -> 164200
A23: Total | C23: =SUM(C12,C22) -> 179850 | D23: =SUM(D12,D22) -> 15646950 | E23: =SUM(E14:E22) -> 0 | F23: =C23-E23 -> 179850
A25: Note: Cost for towing from Khalid Port to Mumbai harbour is not considered.

Sheet Ann II
A1: BUDGETED EXPENSES FOR JINDAL PIONEER RECERTIFICATION & MISCELLANEOUS SERVICES -ANNEXURE II
A2: B | B2: CLASS RELATED EXPENSES
A3: Sr. No. | B3: Description | C3: Budgetory Cost | D3: Actual cost | E3: Budgetory Cost | F3: Local Actual Cost | G3: Local cost in USD | H3: Local cost in INR | I3: Total cost in USD | J3: Surplus/Exceeded | K3: MR NO | L3: PO NO | M3: Remarks | N3: CS VALUE TILL DATE
C4: (in USD) | D4: (in USD) | E4: (in INR)
A6: I | B6: CLASS SURVEY & RELATED EXPENSES
A7: 1 | B7: Spudcan Internal and External anode replacement | C7: =16193 -> 16193 | E7: =C7*87 -> 1408791 | F7: 56597 | H7: 42697.5 | I7: =F7*0.27+G7+H7*0.01149 -> 15771.784 | J7: =C7-I7 -> 421.21573 | K7: RJPSL/BO/2526/00002 RJPDD/BO/2526/00013 | L7: RJPSL/IPO/2526/00001 RJPDD/LPO/2526/00001 | M7: Anode cost- $16192.6 | N7: USD 16192.6 Anode cost
A8: 2 | B8: Donut NDT | C8: 5000 | I8: =F8*0.27+G8+H8*0.01149 -> 0 | J8: =C8-I8 -> 5000
A9: 3 | B9: DNV Survey and Flag charges | C9: 15000 | E9: =C9*87 -> 1305000 | G9: 4850 | I9: =F9*0.27+G9+H9*0.01149 -> 4850 | J9: =C9-I9 -> 10150 | K9: RJPSL/BO/2526/00189 | L9: RJPSL/IPO/2526/00148 | M9: Considered actual amount
A10: Total | C10: =SUM(C7:C9) -> 36193 | E10: =SUM(E7:E9) -> 2713791 | I10: =SUM(I7:I9) -> 20621.784 | J10: =C10-I10 -> 15571.216

Sheet Ann III
A1: BUDGETED EXPENSES FOR JINDAL PIONEER RECERTIFICATION & MISCELLANEOUS SERVICES - ANNEXURE III
A2: A | B2: KHALID AND LAMPRELL PORT EXPENSES
A3: S.No | B3: DESCRIPTION | C3: UOM | D3: Qty | E3: (USD)/Day Lamprell | F3: (USD)/Day Khalid | G3: BUDGETORY COST (USD) LAMPRELL HAMRIYAH (130 DAYS) | H3: BUDGETORY COST (USD) LAMPRELL HAMRIYAH(10 DAYS) AND PORT KHALID(120 DAYS) | I3: BUDGETORY COST (INR) | J3: Actual cost (AED) | K3: Actual cost (USD) | L3: VOR (USD) | M3: Projected cost | N3: Actucal Total Cost (USD) | O3: Surplus/Exceeded | P3: MR NO | Q3: PO NO | R3: Remarks
A4: 1 | B4: Agency Fee | C4: Mon | R4: Considered in CHA- Ann IV SR no 1
A5: 2 | B5: Port Due | C5: Ea | R5: Considered in CHA- Ann IV SR no 1
A6: 3 | B6: Port parking charges | C6: day | D6: 130 | E6: 600 | F6: 450 | G6: =E6*130 -> 78000 | H6: =E6*10+ F6*120 -> 60000 | I6: =H6*87 -> 5220000 | K6: =162*600 -> 97200 | N6: =J6*0.27+K6+L6+M6 -> 97200 | O6: =G6-N6 -> -19200 | R6: Lamprell Hamriyah Charges @ $600 /day for 10 days Khalid Port Charges @ $450/ day for 4 months
A7: 4 | B7: Berthing Charges, Other miscellaneous charges (Fire team),MISCELLANEOUS (STAGING/BARRICADING) | C7: day | D7: 130 | E7: 150 | F7: 200 | G7: =E7*130 -> 19500 | H7: =E7*10 + F7*120 -> 25500 | I7: =H7*87 -> 2218500 | L7: 15000 | N7: =J7*0.27+K7+L7+M7 -> 15000 | O7: =G7-N7 -> 4500 | R7: Lamprell Hamriyah miscellaneous -$150/day Khalid port miscellaneous - $200/day
A8: 5 | B8: Additional shiyard equipment and services | C8: day | D8: 130 | E8: 1750 | F8: 1000 | G8: =E8*130 -> 227500 | H8: =E8*10 + F8*120 -> 137500 | I8: =H8*87 -> 11962500 | L8: =36113+4750+130200 -> 171063 | N8: =J8*0.27+K8+L8+M8 -> 171063 | O8: =G8-N8 -> 56437 | Q8: Ut gauging, MPI Stell replacement Other miscellaneous | R8: Lamprell additional charges- $1750/day Khalid additional charges- $1000/day ($14/hour charges for electricain mechnanic, riggers and other equipment charges - forklift/cranes)
A9: 6 | B9: Pre - handover equipment endurance test | C9: lumpsum | G9: 18000 | H9: 18000 | I9: =H9*87 -> 1566000 | L9: 10000 | N9: =J9*0.27+K9+L9+M9 -> 10000 | O9: =G9-N9 -> 8000 | R9: Estimated
A10: 7 | B10: Catering charges in Lamprell yard pre hand over | C10: day | D10: 45 | E10: 25 | G10: =45*25*15 -> 16875 | H10: =45*25*15 -> 16875 | I10: =H10*87 -> 1468125 | L10: 16875 | N10: =J10*0.27+K10+L10+M10 -> 16875 | O10: =G10-N10 -> 0 | R10: Estimated $25/day considerd for 15 persons for 45 days
A11: Total | G11: =SUM(G6:G10) -> 359875 | H11: =SUM(H6:H10) -> 257875 | I11: =SUM(I4:I10) -> 22435125 | N11: =SUM(N6:N10) -> 310138 | O11: =G11-N11 -> 49737
A12: B
A13: S.No | B13: DESCRIPTION | C13: UOM | D13: (QTY) | E13: (USD) | R13: Remarks
A14: 9 | B14: Lube oil for engines, Mud pump. Hydraulic oil for HPU, KOOMI Unit, Jacking Gearbox etc | C14: BBL | D14: 42 | G14: 100000 | H14: 100000 | I14: =H14*87 -> 8700000 | J14: =113624+36573+29400 -> 179597 | N14: =J14*0.27+K14+L14+M14 -> 48491.19 | O14: =G14-N14 -> 51508.81 | P14: RJPSL/BO/2526/00017 RJPSL/BO/2526/00282 | Q14: RJPSL/IPO/2526/00021, RJPSL/IPO/2526/00098 RJPSL/IPO/2526/00187 RJPSL/IPO/2526/00188 | R14: 15 bbl for 3 nos main Engines & 5 bbl for Jacking system , 5 bbl for Koomey unit, 3 bbl for Drawworks,8 bbls for Mud pump, 1 bbl Compressor oil & 5 bbls contigency.
A15: 10 | B15: Supply of Pot Water in Harbour (Approx.) | C15: MT | D15: 10 | E15: =10*13 -> 130 | G15: =10*140*13 -> 18200 | H15: =10*140*13 -> 18200 | I15: =H15*87 -> 1583400 | J15: =12150+4050+4050 -> 20250 | N15: =J15*0.27+K15+L15+M15 -> 5467.5 | O15: =G15-N15 -> 12732.5 | P15: RJPSL/BO/2627/00001 RJPSL/BO/2526/00470 RJPSL/BO/2526/00345 RJPSL/BO/2526/00029, RJPSL/BO/2526/00118, RJPSL/IPO/2526/00144 | Q15: RJPSL/IPO/2627/00013 RJPSL/IPO/2526/00330 RJPSL/IPO/2526/00226 RJPSL/IPO/2526/00032 RJPSL/IPO/2526/00093 RJPSL/IPO/2526/00144 | R15: Consumption-10MT/day Considered for 140 days at yard at $13/day
A16: 11 | B16: Diesel for Rig | C16: KL | D16: 5 | E16: 800 | G16: =5*800*140 -> 560000 | H16: =5*800*140 -> 560000 | I16: =H16*87 -> 48720000 | K16: =104100+47610+43250+43250+34050 -> 272260 | M16: 250000 | N16: =J16*0.27+K16+L16+M16 -> 522260 | O16: =G16-N16 -> 37740 | P16: RJPSL/BO/2526/00459 RJPSL/BO/2526/00344 RJPSL/BO/2526/00028, RJPSL/BO/2526/00117 | Q16: RJPSL/IPO/2526/00352 RJPSL/IPO/2526/00225 RJPSL/IPO/2526/00031, RJPSL/IPO/2526/00101 | R16: $800 /KL for 5KL for 140 days 110 days at yard & 30 days for tow to mumbai harbour and then to client designated location.
A17: Total | G17: =SUM(G14:G16) -> 678200 | H17: =SUM(H14:H16) -> 678200 | I17: =SUM(I14:I16) -> 59003400 | N17: =SUM(N14:N16) -> 576218.69 | O17: =G17-N17 -> 101981.31
A18: Grand Total | G18: =SUM(G11,G17) -> 1038075 | H18: =SUM(H11,H17) -> 936075 | I18: =SUM(I11,I17) -> 81438525 | N18: =SUM(N11,N17) -> 886356.69 | O18: =SUM(O11,O17) -> 151718.31
B20: All port charges are considered after the handover of the rig from Saipem to Jindal, Post November 24.

Sheet Ann IV
A1: BUDGETED EXPENSES FOR JINDAL PIONEER RECERTIFICATION & MISCELLANEOUS SERVICES- ANNEXURE IV
A2: Clearing Forwarding and Custom Duty Charges
A3: Sr. No. | B3: Description | C3: Budgetory Cost | D3: Budgetory cost | E3: Actual total cost | F3: Surplus/Exceeded | G3: Remarks
C4: (in USD) | D4: (in INR) | E4: (USD)
A6: D | B6: Agency Charges / Transportation
A7: 1 | B7: Overseas Freight & Forwarding Expenses | C7: 200000 | D7: =C7*87 -> 17400000 | E7: =101047+26274 -> 127321 | F7: =C7-E7 -> 72679 | G7: Ref -Jindal Exp 23
A8: 2 | B8: Customs Formalities and customs charges etc | C8: 75000 | D8: =C8*87 -> 6525000 | F8: =C8-E8 -> 75000 | G8: Ref -Jindal Exp 23
A10: Total | C10: =SUM(C7:C8) -> 275000 | D10: =SUM(D7:D8) -> 23925000 | E10: =SUM(E7:E9) -> 127321 | F10: =C10-E10 -> 147679

Sheet Ann V
A1: BUDGETED EXPENSES FOR JINDAL PIONEER RECERTIFICATION & MISCELLANEOUS SERVICES -ANNEXURE V
A2: Crew flights, visa, CDC , Catering , Communication and salary
A3: Sr. No. | B3: Description | C3: Budgetory Cost | D3: Budgetory cost | E3: Actual Total cost | F3: Surplus/Exceeded | G3: Remarks
C4: (in USD) | D4: (in INR) | E4: (in USD)
A6: E | B6: Crew Expenses
A7: 1 | B7: Catering & services onboard | C7: =17*50*150 -> 127500 | D7: =C7*87 -> 11092500 | E7: =3300+16357+20058.5+23710.5+23331 -> 86757 | F7: =C7-E7 -> 40743 | G7: 50 person onboard @ USD 17/ person/ day for 150 days 3Cook @ USD 1050/ month, 4- Steward @ USD 735/ea month - for 6 months
A8: 2 | B8: Crew/Contractor Transport & Accomodation,local and Flight Tickets | C8: 60000 | D8: =C8*87 -> 5220000 | E8: =60500+11150+14910 -> 86560 | F8: =C8-E8 -> -26560 | G8: CDC / VISA Fee, Sign Off / Flight Tickets / Transportation Sign on-off considered for 30crew
A9: 3 | B9: Crew Salary | C9: =3000*60 + 4500*120 -> 720000 | D9: =C9*87 -> 62640000 | E9: =508245+9136 -> 517381 | F9: =C9-E9 -> 202619 | G9: $3000/day considerd for 60 days and $4500/day considered for 120 days.
A10: 4 | B10: Internet for Communication | C10: 10000 | D10: =C10*87 -> 870000 | E10: =1650 -> 1650 | F10: =C10-E10 -> 8350 | G10: Etisalat for 180 days
A12: Total | C12: =SUM(C7:C10) -> 917500 | D12: =SUM(D7:D10) -> 79822500 | E12: =SUM(E7:E10) -> 692348 | F12: =C12-E12 -> 225152

Sheet Ann VI-Drill
A1: BUDGETED EXPENSES FOR JINDAL PIONEER RECERTIFICATION & MISCELLANEOUS SERVICES - ANNEXURE VI
A2: F | C2: Drilling, Well Control and Solid Control
A3: Sr. No. | B3: Material Code | C3: Area | D3: DEPARTMENT / JOB DESCRIPTION | E3: WORK TO BE CARRIED OUT BY | F3: Budgetory Cost (USD) | G3: BUDGETORY COST (INR) | H3: Actual Cost Local (AED) | I3: Actual Cost Local (USD) | J3: Actual Cost Local (INR) | K3: Actual Cost Import (USD) | L3: VOR (USD) | M3: Projected Cost | N3: Actucal Total Cost (USD) | O3: Surplus/Exceeded | P3: MR NO | Q3: PO NO | R3: Remarks | S3: PO VALUE TILL DATE
A4: 1 | B4: 301073001 | C4: Derrick | D4: Derrick/Mast - CAT III inspection ,including TDS Dolly tracks bolt inspection& Drop Survey along with Remedial derrick handrails structural alignment and crown ladder allignment | E4: Third Party | F4: 25000 | G4: =F4*87 -> 2175000 | H4: =6200+4583+3209+4333 -> 18325 | K4: =7898+10530 -> 18428 | L4: 20670 | N4: =H4*0.27+I4+J4*0.01149+K4+L4+M4 -> 44045.75 | O4: =F4-N4 -> -19045.75 | P4: RJPSL/BO/2526/00391 RJPSL/BO/2526/00391 RDDPL/BO/2526/00148 | Q4: RJPSL/IPO/2526/00327, RJPSL/IPO/2526/00328 RJPSL/IPO/2526/00316, RJPSL/IPO/2526/00317 RDDPL/IPO/2526/00124 | R4: Estimated
A5: 2 | B5: 302302001 | C5: Drilling | D5: Crown Block/Cluster sheaves/Fastline/Deadline/Deflector Sheaves - CAT IV | E5: OEM/API | F5: 99918 | G5: =F5*87 -> 8692866 | K5: 97058.98 | N5: =H5*0.27+I5+J5*0.01149+K5+L5+M5 -> 97058.98 | O5: =F5-N5 -> 2859.02 | P5: RDDPL/BO/2526/00008 | Q5: RDDPL/IPO/2526/00049 | R5: CS -ABCO Cost considered as per CS value, cost may increase post D&I
A6: 3 | C6: Texas Deck | D6: Texas Deck - CTU platform | F6: 5000 | G6: =F6*87 -> 435000 | N6: =H6*0.27+I6+J6*0.01149+K6+L6+M6 -> 0 | O6: =F6-N6 -> 5000
A7: 4 | B7: 313314000 | C7: Drilling | D7: Top Drive - Overhual- CAT IV and Commisisioning. | E7: OEM/API | F7: 578164 | G7: =F7*87 -> 50300268 | K7: =566250.43+121625 -> 687875.43 | N7: =H7*0.27+I7+J7*0.01149+K7+L7+M7 -> 687875.43 | O7: =F7-N7 -> -109711.43 | P7: RDDPL/BO/2526/00192 RDDPL/BO/2526/00002 | Q7: RDDPL/IPO/2526/00153 RDDPL/IPO/2526/00045 | R7: PO- NOV Cost considered as per PO value, cost may increase post D&I | S7: 578163.52
C8: Drilling | D8: Well center - Allignement | E8: OEM/API | F8: 10000 | G8: =F8*87 -> 870000 | N8: =H8*0.27+I8+J8*0.01149+K8+L8+M8 -> 0 | O8: =F8-N8 -> 10000 | R8: Estimated
A9: 5 | B9: 303303001 | C9: Drilling | D9: Travelling Block - CAT IV | E9: OEM/API | F9: 81906 | G9: =F9*87 -> 7125822 | K9: =160306-17150 -> 143156 | N9: =H9*0.27+I9+J9*0.01149+K9+L9+M9 -> 143156 | O9: =F9-N9 -> -61250 | P9: RDDPL/BO/2526/00007, RDDPL/BO/2526/00073 | Q9: RDDPL/IPO/2526/00048, RDDPL/IPO/2526/00079 | R9: CS -ABCO Cost considered as per PO value, cost may increase post D&I
A10: 6 | B10: 317317001 | C10: Drilling | D10: Deadline Anchor - CAT IV | E10: OEM/API | F10: 26707 | G10: =F10*87 -> 2323509 | K10: =9832+1450 -> 11282 | N10: =H10*0.27+I10+J10*0.01149+K10+L10+M10 -> 11282 | O10: =F10-N10 -> 15425 | P10: RDDPL/BO/2526/00157 RDDPL/BO/2526/00009, RDDPL/BO/2526/00065 | Q10: RDDPL/IPO/2526/00128 RDDPL/IPO/2526/00003, RDDPL/IPO/2526/00031 | R10: CS -ABCO only for Inspection Cost considered as per CS value, cost may increase post D&I
A11: 7 | B11: 312312001 | C11: Drilling | D11: Draw Works - CAT IV | E11: OEM/API | F11: 567761 | G11: =F11*87 -> 49395207 | K11: 660223 | N11: =H11*0.27+I11+J11*0.01149+K11+L11+M11 -> 660223 | O11: =F11-N11 -> -92462 | P11: RDDPL/BO/2526/00003, RDDPL/BO/2526/00092 | Q11: RDDPL/IPO/2526/00046, RDDPL/IPO/2526/00101 | R11: PO- NOV Cost considered as per PO value, cost may increase post D&I | S11: 567760.57
E12: Brake stop plate to be changed | F12: 57338 | G12: =F12*87 -> 4988406 | K12: 339401 | N12: =H12*0.27+I12+J12*0.01149+K12+L12+M12 -> 339401 | O12: =F12-N12 -> -282063 | P12: RDDPL/BO/2526/00191 | Q12: RDDPL/IPO/2526/00152 | R12: Estimated
A13: 8 | C13: Drilling | D13: Drill line spool | F13: 50000 | G13: =F13*87 -> 4350000 | N13: =H13*0.27+I13+J13*0.01149+K13+L13+M13 -> 0 | O13: =F13-N13 -> 50000 | R13: Estimated
A14: 9 | B14: 313315001 | C14: Drilling | D14: Rotary Table - CAT IV | E14: OEM/API | F14: 73582 | G14: =F14*87 -> 6401634 | H14: 90 | K14: =113222+13920 -> 127142 | N14: =H14*0.27+I14+J14*0.01149+K14+L14+M14 -> 127166.3 | O14: =F14-N14 -> -53584.3 | P14: RDDPL/BO/2526/00006, RDDPL/BO/2526/00114, RDDPL/BO/2526/00091, RDDPL/BO/2526/00113 | Q14: RDDPL/IPO/2526/00002, RDDPL/IPO/2526/00092, RDDPL/IPO/2526/00096, RDDPL/IPO/2526/00097 | R14: CS-ABCO Cost considered as per CS value, cost may increase post D&I
A15: 10 | B15: 325325001 | C15: Drilling | D15: Mud Pumps - CAT IV | E15: OEM/API | F15: 590676 | G15: =F15*87 -> 51388812 | K15: =598770+562+3123+5332 -> 607787 | N15: =H15*0.27+I15+J15*0.01149+K15+L15+M15 -> 607787 | O15: =F15-N15 -> -17111 | P15: RDDPL/BO/2526/00166 RDDPL/BO/2526/00139 RDDPL/BO/2526/00004, RDDPL/BO/2526/00072 | Q15: RDDPL/IPO/2526/00131 RDDPL/IPO/2526/00112 RDDPL/IPO/2526/00047, RDDPL/IPO/2526/00065 | R15: CS-ABCO Cost considered as per CS value, cost may increase post D&I
A16: 11 | B16: 325053001 | C16: Drilling | D16: Iron Roughneck - CAT IV | E16: Third Party | F16: =422047+16575 -> 438622 | G16: =F16*87 -> 38160114 | K16: =432160.46+306676 -> 738836.46 | N16: =H16*0.27+I16+J16*0.01149+K16+L16+M16 -> 738836.46 | O16: =F16-N16 -> -300214.46 | P16: RDDPL/BO/2526/00190 RDDPL/BO/2526/00005 | Q16: RDDPL/IPO/2526/00151 RDDPL/IPO/2526/00004 | R16: CS- NOV Cost considered as per CS value, cost may increase post D&I | S16: 432160.49
A17: 12 | B17: 334334001 | C17: Diverter System | D17: Diverter is due for 5 year recertification with COC | E17: Third Party | F17: 276185.56 | G17: =F17*87 -> 24028144 | K17: =268926.7+35306+111068 -> 415300.7 | N17: =H17*0.27+I17+J17*0.01149+K17+L17+M17 -> 415300.7 | O17: =F17-N17 -> -139115.14 | P17: RDDPL/BO/2526/00137 RDDPL/BO/2526/00022, RDDPL/BO/2526/00130 RDDPL/BO/2526/00001 | Q17: RDDPL/IPO/2526/00113 RDDPL/IPO/2526/00005, RDDPL/IPO/2526/00106 RDDPL/IPO/2526/00040 | R17: CS- OIL STATES Cost considered as per CS value, cost may increase post D&I
A18: 13 | B18: 331331051 | C18: Drilling | D18: 13-5/8" BOP Stack Recertification | E18: Third party | F18: 693364 | G18: =F18*87 -> 60322668 | K18: =693364+48672 -> 742036 | N18: =H18*0.27+I18+J18*0.01149+K18+L18+M18 -> 742036 | O18: =F18-N18 -> -48672 | P18: RDDPL/BO/2526/00144 RDDPL/BO/2526/00010 | Q18: RDDPL/IPO/2526/00127 RDDPL/IPO/2526/00036 | R18: CS- CAMERON SNG Cost considered as per CS value, cost may increase post D&I
A19: 14 | B19: 331331021 | C19: Drilling | D19: 21-1/4" BOP Stack Recertification | E19: Third party | F19: 621572 | G19: =F19*87 -> 54076764 | K19: 621752 | N19: =H19*0.27+I19+J19*0.01149+K19+L19+M19 -> 621752 | O19: =F19-N19 -> -180 | R19: CS- CAMERON SNG Cost considered as per CS value, cost may increase post D&I
A20: 15 | B20: 312312011 | C20: Drilling | D20: Eaton Dynamic brake/Emergency brake inspection and certification | E20: OEM/API | G20: =F20*87 -> 0 | N20: =H20*0.27+I20+J20*0.01149+K20+L20+M20 -> 0 | O20: =F20-N20 -> 0
A21: 16 | B21: 325053001 | C21: Drilling | D21: Mud Pumps - Pulsation Dampeners & Relief Valves | E21: Rig Crew/Third Party | F21: =10000+25000 -> 35000 | G21: =F21*87 -> 3045000 | I21: 1843.82 | K21: =31031.88+567 -> 31598.88 | N21: =H21*0.27+I21+J21*0.01149+K21+L21+M21 -> 33442.7 | O21: =F21-N21 -> 1557.3 | P21: RDDPL/BO/2526/00178 RJPSL/BO/2526/00234 RJPSL/BO/2526/00047 RDDPL/BO/2526/00085 | Q21: RDDPL/IPO/2526/00139 RJPSL/IPO/2526/00305 RJPSL/IPO/2526/00046 RDDPL/IPO/2526/00077 | R21: Estimated
A22: 17 | B22: 337047001 | C22: Drill floor | D22: BOP Test Pump refurbishment | E22: Rig Crew/Third Party | F22: 15000 | G22: =F22*87 -> 1305000 | H22: =3736+672+2946+174+270 -> 7798 | I22: =4736+3828 -> 8564 | J22: 55022 | N22: =H22*0.27+I22+J22*0.01149+K22+L22+M22 -> 11301.663 | O22: =F22-N22 -> 3698.3372 | P22: RJPSL/BO/2526/00378 RJPDD/BO/2526/00280 RJPSL/BO/2526/00378 RJPSL/BO/2526/00383 RJPSL/BO/2526/00362 RJPSL/BO/2526/00059, RJPSL/BO/2526/00253 | Q22: RJPSL/IPO/2627/00010 RJPDD/LPO/2526/00057 RJPSL/IPO/2526/00311 RJPSL/IPO/2526/00296 RJPSL/IPO/2526/00268 RJPSL/IPO/2526/00241 RJPSL/IPO/2526/00134, RJPSL/IPO/2526/00157 | R22: Estimated
A23: 18 | C23: Drill floor | D23: Wireline Unit - Inhouse maintenance | E23: Rig Crew/Third Party | F23: 5000 | G23: =F23*87 -> 435000 | N23: =H23*0.27+I23+J23*0.01149+K23+L23+M23 -> 0 | O23: =F23-N23 -> 5000 | R23: Estimated
A24: 19 | B24: 346348005 | C24: Drill floor | D24: Spinner - Overhauling | E24: Rig Crew/Third Party | F24: 4000 | G24: =F24*87 -> 348000 | N24: =H24*0.27+I24+J24*0.01149+K24+L24+M24 -> 0 | O24: =F24-N24 -> 4000 | R24: Estimated
A25: 20 | C25: Drill floor | D25: Inside BOP Valves - Inspection & Pressure Testing (3-1/2" , 5", 5-1/2") - with Spares | E25: Rig Crew/Third Party | F25: 25000 | G25: =F25*87 -> 2175000 | K25: 60462 | N25: =H25*0.27+I25+J25*0.01149+K25+L25+M25 -> 60462 | O25: =F25-N25 -> -35462 | P25: RDDPL/BO/2526/00088 | Q25: RDDPL/IPO/2526/00086 | R25: Estimated
A26: 21 | C26: Drill floor | D26: FOSVs - Inspection & Pressure Testing (3-1/2 ), with Spares | E26: Rig Crew/Third Party | F26: 10000 | G26: =F26*87 -> 870000 | N26: =H26*0.27+I26+J26*0.01149+K26+L26+M26 -> 0 | O26: =F26-N26 -> 10000 | R26: Estimated
D27: Cup tester | F27: 2400 | G27: =F27*87 -> 208800 | N27: =H27*0.27+I27+J27*0.01149+K27+L27+M27 -> 0 | O27: =F27-N27 -> 2400 | R27: Moulded cup as the codition is deteriorated
A28: 22 | B28: 317077001 | C28: Drill floor | D28: Pile Hammer procurement/ Transfer from sister rig | G28: =F28*87 -> 0 | N28: =H28*0.27+I28+J28*0.01149+K28+L28+M28 -> 0 | O28: =F28-N28 -> 0
A29: 23 | B29: 328053073 | C29: Drill floor | D29: C&K Hoses, Rotary Hoses - Certification /Pressure test with remedial under API 16C & API 7K | E29: Procurement of Choke and kill hoses as per operational requirements | F29: 400000 | G29: =F29*87 -> 34800000 | H29: 25200 | I29: =3808+78425 -> 82233 | N29: =H29*0.27+I29+J29*0.01149+K29+L29+M29 -> 89037 | O29: =F29-N29 -> 310963 | P29: RJPSL/BO/2526/00479 RJPSL/BO/2526/00056 | Q29: RJPSL/IPO/2526/00337 RJPSL/IPO/2526/00104 | R29: Ref: JINDAL STAR DD-23 -Hoses not replaced in the last 6 years. Replacement of Min 6 hoses considered -Added additional $1,00,000 considering increase in cost
A30: 24 | B30: 336336001/325326001 | C30: Well Control | D30: Standpipe Manifold Choke & Kill Manifold valves and Cement Manifold - Recertification | E30: Third Party | F30: =181780+79408 -> 261188 | G30: =F30*87 -> 22723356 | J30: 15600 | K30: =142654+154490+77266+12990 -> 387400 | N30: =H30*0.27+I30+J30*0.01149+K30+L30+M30 -> 387579.24 | O30: =F30-N30 -> -126391.24 | P30: RJPDD/BO/2526/00295 RDDPL/BO/2526/00189 RDDPL/BO/2526/00115 RDDPL/BO/2526/00080 RDDPL/BO/2526/00064 | Q30: RJPDD/LPO/2627/00002 RDDPL/IPO/2526/00143 RDDPL/IPO/2526/00090 RDDPL/IPO/2526/00022 RDDPL/IPO/2526/00058 | R30: CAT IV Ref WOM : JULY 2025 Mud / standpipe manifold - 41,524+21373 Cement Manifoild : 2859+9732 Choke and kill manifold:33275+48303 Hydraulic and manual chokes : 84122 Contingency: 20000
A31: 25 | B31: 332332001/332335001 | C31: Well Control | D31: BOP Control System - Re-Certification - Hydrotest of accumulator bottles,Pressure Vessels, Replacement of bladers and Recertification of Hydraulic hoses and HP lines | E31: Third Party | F31: 500000 | G31: =F31*87 -> 43500000 | H31: =39600 + 35625+4944 -> 80169 | I31: =20050+17343 -> 37393 | K31: =63007 -> 63007 | N31: =H31*0.27+I31+J31*0.01149+K31+L31+M31 -> 122045.63 | O31: =F31-N31 -> 377954.37 | P31: RJPSL/BO/2526/00437 RJPSL/BO/2526/00353 RJPSL/BO/2526/00258 RDDPL/BO/2526/00123 RJPSL/BO/2526/00105, RJPSL/BO/2526/00109, RJPSL/BO/2526/00207, RJPSL/BO/2526/00271 | Q31: RJPSL/IPO/2526/00307 RJPSL/IPO/2526/00260 RJPSL/IPO/2526/00253 RDDPL/IPO/2526/00085 RJPSL/IPO/2526/00075, RJPSL/IPO/2526/00103, RJPSL/IPO/2526/00146, RJPSL/IPO/2526/00195 | R31: 5 yearly certification as per API 16D 3rd edition requirement as per OISD 174 Estimated
A32: 26 | C32: Well Control | D32: Adapter, Spools, Risers, DSA, Procurement Recertification | E32: Third Party | G32: =F32*87 -> 0 | N32: =H32*0.27+I32+J32*0.01149+K32+L32+M32 -> 0 | O32: =F32-N32 -> 0 | R32: Considered in Ann X Sr#26
A33: 27 | C33: Well Control | D33: BOP Side Outlets valves Recertification | E33: Third Party | F33: 30000 | G33: =F33*87 -> 2610000 | I33: 3155.6 | K33: =1445+31860 -> 33305 | N33: =H33*0.27+I33+J33*0.01149+K33+L33+M33 -> 36460.6 | O33: =F33-N33 -> -6460.6 | P33: RDDPL/BO/2526/00170 RJPSL/BO/2526/00120 RDDPL/BO/2526/00136 | Q33: RDDPL/IPO/2526/00134 RJPSL/IPO/2526/00150 RDDPL/IPO/2526/00118 | R33: Estimated
A34: 28 | C34: BOP RAMs | D34: Inventory of BOP RAMs & elastomers to be checked & recertified. | E34: Third Party | F34: 100000 | G34: =F34*87 -> 8700000 | I34: 12800 | K34: 82687 | N34: =H34*0.27+I34+J34*0.01149+K34+L34+M34 -> 95487 | O34: =F34-N34 -> 4513 | P34: RJPSL/BO/2526/00178 RDDPL/BO/2526/00071, RDDPL/BO/2526/00106, RDDPL/BO/2526/00098 | Q34: RJPSL/IPO/2526/00121 RDDPL/IPO/2526/00068, RDDPL/IPO/2526/00076, RDDPL/IPO/2526/00095 | R34: Estimated
A35: 29 | C35: HP Hoses | D35: HP Hose recertification (14 No.) and repalcement if rejected - Accounted in Hose Register | E35: Third Party | G35: =F35*87 -> 0 | K35: 162.5 | N35: =H35*0.27+I35+J35*0.01149+K35+L35+M35 -> 162.5 | O35: =F35-N35 -> -162.5 | P35: RDDPL/BO/2526/00076 | Q35: RDDPL/IPO/2526/00066 | R35: Considered in Sr#24
A36: 30 | C36: Mud System | D36: Solid control system - Shale shakers (3 No), Desander, Desilter , Mud cleaner,Mud agitator Degasser,Gumbo shaker, Shale shaker baskets & gates | E36: Third party/ Rig crew | F36: 250000 | G36: =F36*87 -> 21750000 | H36: =9831+3796 -> 13627 | K36: =98384+4000 -> 102384 | N36: =H36*0.27+I36+J36*0.01149+K36+L36+M36 -> 106063.29 | O36: =F36-N36 -> 143936.71 | P36: RJPSL/BO/2526/00400 RDDPL/BO/2526/00176 RJPSL/BO/2526/00108, RJPSL/BO/2526/00206, RJPSL/BO/2526/00269, RJPSL/BO/2526/00265 RDDPL/BO/2526/00026, RDDPL/BO/2526/00027, RDDPL/BO/2526/00061, RDDPL/BO/2526/00086 | Q36: RJPSL/IPO/2526/00329 RDDPL/IPO/2526/00130 RJPSL/IPO/2526/00087, RJPSL/IPO/2526/00177, RJPSL/IPO/2526/00180, RJPSL/IPO/2526/00197 RDDPL/IPO/2526/00008, RDDPL/IPO/2526/00009, RDDPL/IPO/2526/00070, RDDPL/IPO/2526/00075 | R36: Overhaul -Estimated Shale Shakers, Cutting dryer, Augers for Dryer & Shakers, Feed Pumps, Centrifugfes, Degasser, Vaccum compressor, Poor Buoy
B37: 326342001 | E37: Shale Shaker basket | F37: =55000*2 -> 110000 | G37: =F37*87 -> 9570000 | K37: 110000 | N37: =H37*0.27+I37+J37*0.01149+K37+L37+M37 -> 110000 | O37: =F37-N37 -> 0 | P37: RDDPL/BO/2526/00134 | Q37: RDDPL/IPO/2526/00110 | R37: Ref Star DD New Basket cost from Import, USD 55000
A38: 31 | B38: 326025001 | C38: Mud System | D38: Centrifuges-Major Overhaul required | E38: Third party | F38: 60000 | G38: =F38*87 -> 5220000 | J38: 18000 | K38: 5113.6 | N38: =H38*0.27+I38+J38*0.01149+K38+L38+M38 -> 5320.42 | O38: =F38-N38 -> 54679.58 | P38: RJPDD/BO/2526/00273 RDDPL/BO/2526/00063 | Q38: RJPDD/LPO/2526/00052 RDDPL/IPO/2526/00029 | R38: Considered in Sr#30
A39: 32 | B39: 324026001/324026001 | C39: Mud System | D39: Mud tank Agitators and Mud guns- Overhauling & need to replace some off fan blades | G39: =F39*87 -> 0 | N39: =H39*0.27+I39+J39*0.01149+K39+L39+M39 -> 0 | O39: =F39-N39 -> 0 | R39: Considered in Sr#30
A40: 33 | B40: 324 | C40: Mud System | D40: Mixing Hopper & Mixer-Overhauling & Testing | E40: Rig Crew | G40: =F40*87 -> 0 | N40: =H40*0.27+I40+J40*0.01149+K40+L40+M40 -> 0 | O40: =F40-N40 -> 0 | R40: Considered in Sr#30
A41: 34 | B41: 324021001 | C41: Mud System | D41: Cutting Dryer and Auger ,Overahauling & Testing | E41: Rig Crew | G41: =F41*87 -> 0 | N41: =H41*0.27+I41+J41*0.01149+K41+L41+M41 -> 0 | O41: =F41-N41 -> 0 | R41: Considered in Sr#30
A42: 35 | C42: Mud System | D42: Feed/Mono Pumps - Overahauling & Testing | E42: Rig Crew | G42: =F42*87 -> 0 | N42: =H42*0.27+I42+J42*0.01149+K42+L42+M42 -> 0 | O42: =F42-N42 -> 0 | R42: Considered in Sr#30
A43: 36 | B43: 373069001 | C43: Mud System | D43: Mud Lab & Instruments - need to be replaced,Inventory to be checked & calibration to be done | E43: Rig Crew/Third Party | G43: =F43*87 -> 0 | N43: =H43*0.27+I43+J43*0.01149+K43+L43+M43 -> 0 | O43: =F43-N43 -> 0 | R43: Considered in Sr#30
A44: 37 | C44: Cementing | D44: Cementing Unit Operational Spares | E44: Third Party | G44: =F44*87 -> 0 | N44: =H44*0.27+I44+J44*0.01149+K44+L44+M44 -> 0 | O44: =F44-N44 -> 0 | R44: Considered in Annexure X Sr#24
A45: 38 | C45: Cementing | D45: Batch Mixer Procurement | G45: =F45*87 -> 0 | N45: =H45*0.27+I45+J45*0.01149+K45+L45+M45 -> 0 | O45: =F45-N45 -> 0 | R45: Considered in Annexure X Sr#24
A46: 39 | C46: Cementing | D46: Transmission Overhaul with testing - 2nos | E46: Third Party | G46: =F46*87 -> 0 | N46: =H46*0.27+I46+J46*0.01149+K46+L46+M46 -> 0 | O46: =F46-N46 -> 0 | R46: Considered in Annexure X Sr#24
A47: 40 | C47: Cementing | D47: Treating Irons MPI/UT/ Pressure test with Certification | E47: Third Party | G47: =F47*87 -> 0 | N47: =H47*0.27+I47+J47*0.01149+K47+L47+M47 -> 0 | O47: =F47-N47 -> 0 | R47: Considered in Annexure X Sr#24
A48: 41 | C48: Cementing | D48: 2" & 1" Plug valves, 1" Auto Choke Overhauling & MPI/UT/ Pressure test pressure test | E48: Third Party | G48: =F48*87 -> 0 | N48: =H48*0.27+I48+J48*0.01149+K48+L48+M48 -> 0 | O48: =F48-N48 -> 0 | R48: Considered in Annexure X Sr#24
A49: 42 | C49: Cementing | D49: Instrumentation- Data Logger, Manual Chart Recorder, PRVs, Transducers, Sensors, Weight indicators | E49: Third Party | G49: =F49*87 -> 0 | N49: =H49*0.27+I49+J49*0.01149+K49+L49+M49 -> 0 | O49: =F49-N49 -> 0 | R49: Considered in Annexure X Sr#24
A50: 43 | B50: 347347001 | C50: Handling Equipment | D50: Handling Tools - CAT IV | E50: Third Party | F50: 100000 | G50: =F50*87 -> 8700000 | I50: 22277.5 | K50: =1307+11563+103.58 -> 12973.58 | N50: =H50*0.27+I50+J50*0.01149+K50+L50+M50 -> 35251.08 | O50: =F50-N50 -> 64748.92 | P50: RDDPL/BO/2526/00145 RJPSL/BO/2526/00057 | Q50: RDDPL/IPO/2526/00145 RJPSL/IPO/2526/00119 | R50: Estimated cost for CAT IV, replacement / repair/ rejections
A51: 44 | B51: 355355001 | C51: Jars | D51: Drilling Jars and Intensifiers overhauling | E51: Third Party | F51: 100000 | G51: =F51*87 -> 8700000 | I51: 24510 | N51: =H51*0.27+I51+J51*0.01149+K51+L51+M51 -> 24510 | O51: =F51-N51 -> 75490 | P51: RJPSL/BO/2526/00443 RJPSL/BO/2526/00093 | Q51: RJPSL/IPO/2526/00363 RJPSL/IPO/2526/00135 | R51: Ref: JSUP DD 2023 : SPARES : USD 54000 and additional Estimated cost for repair . Capital expenditaure in case of total rejection is not considered
A52: 45 | B52: 454042010 | C52: Forklift | D52: Forklift new purchase | E52: Procurement | F52: 17000 | G52: =F52*87 -> 1479000 | J52: 13376 | N52: =H52*0.27+I52+J52*0.01149+K52+L52+M52 -> 153.69024 | O52: =F52-N52 -> 16846.31 | P52: RJPDD/BO/2526/00281 | Q52: RJPDD/LPO/2526/00058 | R52: On-board forklift non-functional
A53: 46 | B53: 365042001 | C53: Winches | D53: 7 Utility Winches, 3Man riders , 2 derrick winches and 3 rig floor winches,CSB wire rope- Wire rope renewal, | E53: Rig crew /Third party | F53: 75000 | G53: =F53*87 -> 6525000 | H53: 401626 | K53: 1065 | N53: =H53*0.27+I53+J53*0.01149+K53+L53+M53 -> 109504.02 | O53: =F53-N53 -> -34504.02 | P53: RDDPL/BO/2526/00183 RJPSL/BO/2526/00064, RJPSL/BO/2526/00065, RJPSL/BO/2526/00066, RJPSL/BO/2526/00184 | Q53: RDDPL/IPO/2526/00155 RJPSL/IPO/2526/00056, RJPSL/IPO/2526/00057, RJPSL/IPO/2526/00058, RJPSL/IPO/2526/00198 | R53: REF: JINDAL STAR DD-2023 : Including spares , inspection & services
A54: 47 | C54: MISC | D54: Other MISC Spares and services plus Punch point clearance | E54: Inhouse | G54: =F54*87 -> 0 | N54: =H54*0.27+I54+J54*0.01149+K54+L54+M54 -> 0 | O54: =F54-N54 -> 0 | R54: Considered in ANN- X SR NO -20 once contract awarded
A55: 48 | C55: Shooting nipple | D55: Shooting Nipple material compliant to API and NACE standards | E55: Third party | G55: =F55*87 -> 0 | N55: =H55*0.27+I55+J55*0.01149+K55+L55+M55 -> 0 | O55: =F55-N55 -> 0 | R55: Considered in Annexure X Sr#41
A56: 49 | C56: Miscellaneous Drill floor equipment | D56: Brake cooling pump, Heat exchanger, Well head connection, | E56: Third party | F56: 100000 | G56: =F56*87 -> 8700000 | H56: =162+695 -> 857 | K56: =3241+982 -> 4223 | N56: =H56*0.27+I56+J56*0.01149+K56+L56+M56 -> 4454.39 | O56: =F56-N56 -> 95545.61 | P56: RDDPL/BO/2526/00167 RDDPL/BO/2526/00164 RJPSL/BO/2526/00436 | Q56: RDDPL/IPO/2526/00133 RDDPL/IPO/2526/00132 RJPSL/IPO/2526/00300 | R56: Estimated
A57: 50 | C57: Chikson and lines | D57: 2'' -10K 15O2, 3"- 5K 602 Re-certification and procurement | E57: Third party | F57: 50000 | G57: =F57*87 -> 4350000 | H57: 44584 | J57: 2459645 | N57: =H57*0.27+I57+J57*0.01149+K57+L57+M57 -> 40299.001 | O57: =F57-N57 -> 9700.9989 | P57: RJPDD/BO/2526/00100 RJPSL/BO/2526/00068, RJPSL/BO/2526/00079, RJPSL/BO/2526/00085 | Q57: RJPDD/LPO/2526/00026 RJPDD/LPO/2526/00018 RJPSL/IPO/2526/00060, RJPSL/IPO/2526/00076, RJPSL/IPO/2526/00078 | R57: Estimated
A58: 51 | C58: Drilling | D58: BOP/DSA/Risers/Diverter Studs & Nut | E58: Third party | F58: 20000 | G58: =F58*87 -> 1740000 | H58: 5696 | I58: 14480 | J58: 37830 | N58: =H58*0.27+I58+J58*0.01149+K58+L58+M58 -> 16452.587 | O58: =F58-N58 -> 3547.4133 | P58: RJPSL/BO/2526/00185, RJPSL/BO/2526/00058, RJPSL/BO/2526/00202 | Q58: RJPSL/IPO/2526/00115, RJPSL/IPO/2526/00118, RJPSL/IPO/2526/00137 | R58: Estimated
A59: 52 | C59: Drilling | D59: Conductor tensioning unit service and overhaul | E59: Rig crew | F59: 5000 | G59: =F59*87 -> 435000 | N59: =H59*0.27+I59+J59*0.01149+K59+L59+M59 -> 0 | O59: =F59-N59 -> 5000 | R59: Estimated
A60: 53 | C60: Drilling | D60: Block hanging line recertification / tong line procurement | E60: Rig crew | F60: 5000 | G60: =F60*87 -> 435000 | H60: =7935.36+4015 -> 11950.36 | N60: =H60*0.27+I60+J60*0.01149+K60+L60+M60 -> 3226.5972 | O60: =F60-N60 -> 1773.4028 | P60: RJPSL/BO/2526/00427 RJPSL/BO/2526/00195 RJPSL/BO/2526/00092 | Q60: RJPSL/IPO/2526/00297 RJPSL/IPO/2526/00166 RJPSL/IPO/2526/00181 | R60: Estimated
A61: 52 | C61: Drill floor | D61: Pipe racking floor wood - Installation | E61: Third Party | G61: =F61*87 -> 0 | N61: =H61*0.27+I61+J61*0.01149+K61+L61+M61 -> 0 | O61: =F61-N61 -> 0 | R61: Considered in Annexure X Sr#25
A62: Total | F62: =SUM(F4:F61) -> 6475383.6 | G62: =SUM(G4:G61) -> 5.6335837e+08 | M62: =SUM(M4:M61) -> 0 | N62: =SUM(N4:N61) -> 6527134 | O62: =F62-N62 -> -51750.472

Sheet Ann VII-Mech
A1: BUDGETED EXPENSES FOR JINDAL PIONEER RECERTIFICATION & MISCELLANEOUS SERVICES- ANNEXURE VII
A2: G | C2: MECHANICAL
A3: Sr. No. | B3: Material Code | C3: Area | D3: DEPARTMENT / JOB DESCRIPTION | E3: WORK TO BE CARRIED OUT BY | F3: Budgetory Cost (USD) | G3: BUDGETORY COST (INR) | H3: Actual Local Cost (AED) | I3: Actual Local Cost (USD) | J3: Actual Local Cost (INR) | K3: Actual Cost Import (USD) | L3: Projected Cost | M3: Actucal Total Cost (USD) | N3: Surplus/Exceeded | O3: MR NO | P3: PO NO | Q3: Remarks
A4: 1 | B4: 65160000 | C4: Engine | D4: Engine MOH- 3 engines | E4: Third party | F4: =(191999*3)+150000+60000 -> 785997 | G4: =F4*87 -> 68381739 | H4: 4637 | J4: 12404 | K4: =254422.63*3 + 144071.18 +92834+5912+10904.9+1769+5262 -> 1024021 | M4: =H4*0.27+I4+J4*0.01149+K4 -> 1025415.5 | N4: =F4-M4 -> -239418.48 | O4: RJPDD/BO/2526/00301 RDDPL/BO/2526/00179 RDDPL/BO/2526/00174 RDDPL/BO/2526/00156 RJPSL/BO/2526/00290 RDDPL/BO/2526/00034, RDDPL/BO/2526/00011, RDDPL/BO/2526/00012, RDDPL/BO/2526/00013, RDDPL/BO/2526/00014, RDDPL/BO/2526/00127 RDDPL/BO/2526/00152 | P4: RJPDD/BO/2526/00301 RDDPL/IPO/2526/00146 RDDPL/IPO/2526/00135 RDDPL/IPO/2526/00129 RJPSL/IPO/2526/00214 RDDPL/IPO/2526/00020, RDDPL/IPO/2526/00037, RDDPL/IPO/2526/00038, RDDPL/IPO/2526/00039, RDDPL/IPO/2526/00050, RDDPL/IPO/2526/00109 RDDPL/IPO/2526/00117 | Q4: PO- ENERIA MOH spare cost Considered for Engines- #1 ,#2 , #4- $191999/Engine MOH spare cost considred for Engine - #3 and #5- $75000/Engine Service cost - $60000 (5 engines)
A5: 2 | B5: 651620020 | C5: Cooling system | D5: Engine radiator System overhaul | E5: Rig crew | F5: 50000 | I5: =63429+6036 -> 69465 | M5: =H5*0.27+I5+J5*0.01149+K5 -> 69465 | N5: =F5-M5 -> -19465 | O5: RJPSL/BO/2526/00411 RJPSL/BO/2526/00041, RJPSL/BO/2526/00040 | P5: RJPSL/IPO/2526/00277 RJPSL/IPO/2526/00042, RJPSL/IPO/2526/00110 | Q5: ESTIMATED
A6: 3 | B6: 651620011 | C6: Air system | D6: Need to be overhaul and General service all 3 Air compressor | E6: Rig crew | F6: 100000 | H6: 1862 | K6: 29966.17 | M6: =H6*0.27+I6+J6*0.01149+K6 -> 30468.91 | N6: =F6-M6 -> 69531.09 | O6: RJPSL/BO/2526/00208 RDDPL/BO/2526/00104 | P6: RJPSL/IPO/2526/00132 RDDPL/IPO/2526/00071 | Q6: ESTIMATED
A7: 4 | B7: 651620011 | C7: Air system | D7: Air dryers need to be overhaul(service air dryer & Bulk air dryer) | E7: Rig crew | F7: 25000 | H7: 6500 | K7: 8250 | M7: =H7*0.27+I7+J7*0.01149+K7 -> 10005 | N7: =F7-M7 -> 14995 | O7: RJPSL/BO/2526/00505 RDDPL/BO/2526/00121 | P7: RJPSL/IPO/2627/00012 RDDPL/IPO/2526/00141 | Q7: ESTIMATED
A8: 5 | B8: 651620011 | C8: Air system | D8: Cold Start Compressor - Overhauling & Testing | E8: Rig crew | F8: 10000 | M8: =H8*0.27+I8+J8*0.01149+K8 -> 0 | N8: =F8-M8 -> 10000 | Q8: ESTIMATED
A9: 6 | C9: Auxiliary Pumps | D9: All the pumps(Mud mixing, mud charging, fire /sea water/Drill water/foam & deluge pump , foam pump , Degasser, Desilter, mud clener pumps, Trip tank pumps, Base oil & break cooling pumps, fuel service & transfer pumps ,Brine Pump,speck pumps need to service & overhual | E9: Rig Crew/Third party | F9: 50000 | H9: =1298+1815 -> 3113 | K9: =36072+80652+123 -> 116847 | M9: =H9*0.27+I9+J9*0.01149+K9 -> 117687.51 | N9: =F9-M9 -> -67687.51 | O9: RDDPL/BO/2526/00165 RJPSL/BO/2526/00489 RDDPL/BO/2526/00160 RJPSL/BO/2526/00115 RDDPL/BO/2526/00082, RDDPL/BO/2526/00050, RDDPL/BO/2526/00070, RDDPL/BO/2526/00069 | P9: RDDPL/IPO/2526/00144 RJPSL/IPO/2526/00354 RDDPL/IPO/2526/00119 RJPSL/IPO/2526/00091 RDDPL/IPO/2526/00023, RDDPL/IPO/2526/00033, RDDPL/IPO/2526/00063, RDDPL/IPO/2526/00069 | Q9: ESTIMATED
A10: 7 | C10: Water maker | D10: Water Maker - Need to be overhaul, service and remedial spare parts | E10: Rig crew | F10: 50000 | H10: 144 | K10: =3496.27+2520 -> 6016.27 | M10: =H10*0.27+I10+J10*0.01149+K10 -> 6055.15 | N10: =F10-M10 -> 43944.85 | O10: RDDPL/BO/2526/00194 RJPSL/BO/2526/00179 RDDPL/BO/2526/00068 | P10: RDDPL/IPO/2526/00154 RJPSL/IPO/2526/00143 RDDPL/IPO/2526/00067 | Q10: ESTIMATED
A11: 8 | B11: 803047001 | C11: Deck equipment | D11: Bilge system pumps - Overhaul & Testing | E11: Rig crew | F11: 25000 | H11: 2730 | M11: =H11*0.27+I11+J11*0.01149+K11 -> 737.1 | N11: =F11-M11 -> 24262.9 | O11: RJPSL/BO/2526/00020 | P11: RJPSL/IPO/2526/00023 | Q11: ESTIMATED
A12: 9 | B12: 702045001 | C12: Deck equipment | D12: Diesel Oil Purifier - Overhaul/ one Drive motor procurement to be done. | E12: Rig crew | F12: 25000 | K12: 2245 | M12: =H12*0.27+I12+J12*0.01149+K12 -> 2245 | N12: =F12-M12 -> 22755 | O12: RDDPL/BO/2526/00057 | P12: RDDPL/IPO/2526/00032 | Q12: ESTIMATED
A13: 10 | B13: 721047001 | C13: Deep well | D13: Deep Well Pumps , Deep well manifold & strainer modification by 3rd party - Overhaul & Testing | E13: Third party | F13: 10000 | H13: 4320 | K13: 7049.85 | M13: =H13*0.27+I13+J13*0.01149+K13 -> 8216.25 | N13: =F13-M13 -> 1783.75 | O13: RDDPL/BO/2526/00140 RJPSL/BO/2526/00246 | P13: RDDPL/IPO/2526/00126 RJPSL/IPO/2526/00174 | Q13: ESTIMATED
D14: New purchase of 2 deep well pumps | M14: =H14*0.27+I14+J14*0.01149+K14 -> 0 | N14: =F14-M14 -> 0 | Q14: ESTIMATED
A15: 12 | B15: 444047001 | C15: Deck equipment | D15: High Pressure Washers- Overhauling & Testing | E15: Rig crew | F15: 10000 | H15: 8785 | J15: 850000 | M15: =H15*0.27+I15+J15*0.01149+K15 -> 12138.45 | N15: =F15-M15 -> -2138.45 | O15: RJPDD/BO/2526/00210 RJPSL/BO/2526/00116 | P15: RJPDD/LPO/2526/00030 RJPSL/IPO/2526/00092 | Q15: ESTIMATED
A16: 13 | B16: 445074001 | C16: Deck equipment | D16: Garbage Compactor - Overhaul & Testing | E16: Rig crew | F16: 10000 | M16: =H16*0.27+I16+J16*0.01149+K16 -> 0 | N16: =F16-M16 -> 10000 | Q16: ESTIMATED
A17: 14 | C17: Deck equipment | D17: Macerator - Overhaul & Testing | E17: Rig crew | F17: 10000 | K17: 15834.74 | M17: =H17*0.27+I17+J17*0.01149+K17 -> 15834.74 | N17: =F17-M17 -> -5834.74 | O17: RDDPL/BO/2526/00116 | P17: RDDPL/IPO/2526/00103 | Q17: ESTIMATED
A18: 15 | B18: 301301001 | C18: Drill floor | D18: Casing Stabbing Board - need to be service,recertified. | E18: Rig crew | F18: 25000 | H18: 8727 | M18: =H18*0.27+I18+J18*0.01149+K18 -> 2356.29 | N18: =F18-M18 -> 22643.71 | O18: RJPSL/BO/2526/00319 | P18: RJPSL/IPO/2526/00223 | Q18: ESTIMATED
A19: 16 | B19: 385 | C19: Drill floor | D19: Main HPU - need to be service, replace all hydrulic control hoses,replace heat echanger assy, | E19: Rig Crew | F19: 50000 | K19: 6954 | M19: =H19*0.27+I19+J19*0.01149+K19 -> 6954 | N19: =F19-M19 -> 43046 | O19: RDDPL/BO/2526/00112, RDDPL/BO/2526/00112 | P19: RDDPL/IPO/2526/00087, RDDPL/IPO/2526/00088 | Q19: ESTIMATED
A20: 17 | B20: 312071001 | C20: Drill floor | D20: Drawwork Air Intensifier - need to be overhauled | E20: Rig Crew | F20: 50000 | K20: 18492.42 | M20: =H20*0.27+I20+J20*0.01149+K20 -> 18492.42 | N20: =F20-M20 -> 31507.58 | O20: RDDPL/BO/2526/00062 | P20: RDDPL/IPO/2526/00030 | Q20: ESTIMATED
A21: 18 | B21: 342349001 | C21: Drill floor | D21: Cathead - need to be overhaul hydraulic cylinders | E21: Rig crew | F21: 50000 | H21: 2561 | K21: 15770 | M21: =H21*0.27+I21+J21*0.01149+K21 -> 16461.47 | N21: =F21-M21 -> 33538.53 | O21: RJPSL/BO/2526/00111 RDDPL/BO/2526/00102, RDDPL/BO/2526/00125 | P21: RJPSL/IPO/2526/00088 RDDPL/IPO/2526/00061, RDDPL/IPO/2526/00105 | Q21: ESTIMATED
A22: 19 | C22: Drill floor | D22: Hydraulic & Pnuematic Hoses( BOP Hoist etc) - Inspection & Replacement | E22: Rig crew/Third Party | F22: 50000 | H22: =41305.02+21774 -> 63079.02 | I22: 4800 | K22: 2419.46 | M22: =H22*0.27+I22+J22*0.01149+K22 -> 24250.795 | N22: =F22-M22 -> 25749.205 | O22: RJPSL/BO/2526/00350 RJPSL/BO/2526/00338 RJPSL/BO/2526/00242 RDDPL/BO/2526/00119 | P22: RJPSL/IPO/2526/00283 RJPSL/IPO/2526/00273 RJPSL/IPO/2526/00263 RDDPL/IPO/2526/00089 | Q22: ESTIMATED
A23: 20 | B23: 365042001/365042003 | C23: Hoisting | D23: Utility Winches , manriding winch including Derrick Winch - Overhauling | E23: Third party | M23: =H23*0.27+I23+J23*0.01149+K23 -> 0 | N23: =F23-M23 -> 0 | Q23: Considered in Annexure VI SR no- 46
A24: 21 | B24: 365042012 | C24: Hoisting | D24: Manrider Winches - Overhauling | M24: =H24*0.27+I24+J24*0.01149+K24 -> 0 | N24: =F24-M24 -> 0 | Q24: Considered in Annexure VI SR no- 46
A25: 22 | B25: 36404201 | C25: Hoisting | D25: BOP hoist overhaul and load test Replace all Air supply hoses & control lines hoses | E25: Third party | F25: 100000 | H25: =5774+26077.5 -> 31851.5 | K25: 44477 | M25: =H25*0.27+I25+J25*0.01149+K25 -> 53076.905 | N25: =F25-M25 -> 46923.095 | O25: RJPSL/BO/2526/00355 RJPSL/BO/2526/00388 RDDPL/BO/2526/00105, RDDPL/BO/2526/00126 | P25: RJPSL/IPO/2526/00284 RJPSL/IPO/2526/00265 RDDPL/IPO/2526/00078, RDDPL/IPO/2526/00094 | Q25: ESTIMATED
A26: 23 | B26: 3610 | C26: Deck Crane | D26: Visually inspection/Overhaul of all winch gear boxes- Slew, Luff, Boom | E26: Third party | F26: 100000 | M26: =H26*0.27+I26+J26*0.01149+K26 -> 0 | N26: =F26-M26 -> 100000 | Q26: ESTIMATED
A27: 24 | B27: 803025001 | C27: Mechanical | D27: OWS - Overhauling | E27: Rig crew | F27: 25000 | H27: 9695 | M27: =H27*0.27+I27+J27*0.01149+K27 -> 2617.65 | N27: =F27-M27 -> 22382.35 | O27: RJPSL/BO/2526/00194, RJPSL/BO/2526/00225 | P27: RJPSL/IPO/2526/00123, RJPSL/IPO/2526/00126 | Q27: ESTIMATED
A28: 25 | B28: 582040001 | C28: Mechanical | D28: Sewage Treatment - Overhauling required one aeration blower required and remedial spares required | E28: Rig crew | F28: 25000 | H28: 3680 | K28: =11231+19227.23 -> 30458.23 | M28: =H28*0.27+I28+J28*0.01149+K28 -> 31451.83 | N28: =F28-M28 -> -6451.83 | O28: RJPSL/BO/2526/00280 RDDPL/BO/2526/00107, RDDPL/BO/2526/00107, RDDPL/BO/2526/00122 | P28: RJPSL/IPO/2526/00184 RDDPL/IPO/2526/00081, RDDPL/IPO/2526/00082, RDDPL/IPO/2526/00100 | Q28: ESTIMATED
A29: 26 | C29: Mechanical | D29: Sanitary System- Overhauling required and remedial spares required | E29: Rig Crew/Third party | F29: 25000 | H29: 4165 | M29: =H29*0.27+I29+J29*0.01149+K29 -> 1124.55 | N29: =F29-M29 -> 23875.45 | O29: RJPSL/BO/2526/00278 | P29: RJPSL/IPO/2526/00183 | Q29: ESTIMATED
A30: 27 | C30: Mechanical | D30: Fire pumps- complete overhaul | E30: Third party | F30: 25000 | H30: =2700+500 -> 3200 | M30: =H30*0.27+I30+J30*0.01149+K30 -> 864 | N30: =F30-M30 -> 24136 | O30: RJPSL/BO/2526/00433 RJPSL/BO/2526/00299 | P30: RJPSL/IPO/2526/00295 RJPSL/IPO/2526/00249 | Q30: ESTIMATED
A31: 28 | C31: Mechanical | D31: Potable Water System - Overhauling | E31: Rig crew | F31: 25000 | H31: 3087 | I31: 7825.56 | K31: 12690 | M31: =H31*0.27+I31+J31*0.01149+K31 -> 21349.05 | N31: =F31-M31 -> 3650.95 | O31: RJPSL/BO/2526/00216 RJPSL/BO/2526/00337 RDDPL/BO/2526/00059 | P31: RJPSL/IPO/2526/00278 RJPSL/IPO/2526/00255 RDDPL/IPO/2526/00027 | Q31: ESTIMATED
A32: 29 | B32: 196062005 | C32: Mechanical | D32: Tools/Fittings/Consumables/Machining equipments | E32: Third party | F32: 50000 | H32: =100707+194+2580 -> 103481 | I32: 20979 | J32: 618188 | K32: 993 | M32: =H32*0.27+I32+J32*0.01149+K32 -> 57014.85 | N32: =F32-M32 -> -7014.8501 | O32: RJPSL/BO/2526/00396 RJPSL/BO/2526/00329 RJPSL/BO/2526/00295 RJPDD/BO/2526/00186, RJPDD/BO/2526/00188, RJPDD/BO/2526/00239, RJPDD/BO/2526/00247 RDDPL/BO/2526/00025 RJPSL/BO/2526/00007, RJPSL/BO/2526/00018, RJPSL/BO/2526/00024, RJPSL/BO/2526/00030, RJPSL/BO/2526/00042, RJPSL/BO/2526/00060, RJPSL/BO/2526/00063, RJPSL/BO/2526/00102, RJPSL/BO/2526/00104, RJPSL/BO/2526/00124, RJPSL/BO/2526/00169, RJPSL/BO/2526/00122, RJPSL/BO/2526/00171, RJPSL/BO/2526/00186, RJPSL/BO/2526/00180, RJPSL/BO/2526/00172, RJPSL/BO/2526/00205, RJPSL/BO/2526/00172, RJPSL/BO/2526/00183, RJPSL/BO/2526/00291, RJPSL/BO/2526/00286 | P32: RJPSL/IPO/2526/00266 RJPSL/IPO/2526/00252 RJPSL/IPO/2526/00247 RJPDD/LPO/2526/00005, RJPDD/LPO/2526/00007, RJPDD/LPO/2526/00029, RJPDD/LPO/2526/00032 RDDPL/IPO/2526/00052 RJPSL/IPO/2526/00007, RJPSL/IPO/2526/00022, RJPSL/IPO/2526/00028, RJPSL/IPO/2526/00033, RJPSL/IPO/2526/00043, RJPSL/IPO/2526/00052, RJPSL/IPO/2526/00055, RJPSL/IPO/2526/00074, RJPSL/IPO/2526/00084, RJPSL/IPO/2526/00095, RJPSL/IPO/2526/00109, RJPSL/IPO/2526/00111, RJPSL/IPO/2526/00112, RJPSL/IPO/2526/00116, RJPSL/IPO/2526/00122, RJPSL/IPO/2526/00129, RJPSL/IPO/2526/00131, RJPSL/IPO/2526/00139, RJPSL/IPO/2526/00161, RJPSL/IPO/2526/00202, RJPSL/IPO/2526/00203 | Q32: ESTIMATED
A33: Total | F33: =SUM(F4:F32) -> 1760997 | G33: =SUM(G4:G32) -> 68381739 | M33: =SUM(M4:M32) -> 1534282.4 | N33: =F33-M33 -> 226714.6

Sheet Ann VIII-Elec
A1: BUDGETED EXPENSES FOR JINDAL PIONEER RECERTIFICATION & MISCELLANEOUS SERVICES -ANNEXURE IX
A2: H | B2: Electrical and Power Plant
A3: Sr. No. | B3: Material Code | C3: Area | D3: DEPARTMENT / JOB DESCRIPTION | E3: WORK TO BE CARRIED OUT BY | F3: Budgetory Cost (USD) | G3: BUDGETORY COST (INR) | H3: Actual cost Local (AED) | I3: Actual cost Local (USD) | J3: Actual cost Local (INR) | K3: Actual cost Import (USD) | L3: VOR (USD) | M3: Projected Cost | N3: Actucal Total Cost (USD) | O3: Surplus/Exceeded | P3: MR NO | Q3: PO NO | R3: Remarks
A4: 1 | B4: 651600000 | C4: Alternators | D4: NOV alternator - 5nos, (Overhauling) | E4: Third party | F4: 50000 | G4: =F4*87 -> 4350000 | H4: =136391+5300+8600 -> 150291 | J4: =160000+46600 -> 206600 | K4: 5556 | N4: =H4*0.27+I4+J4*0.01149+K4+L4 -> 48508.404 | O4: =F4-N4 -> 1491.596 | P4: RJPSL/BO/2526/00458 RJPDD/BO/2526/00237 RJPDD/BO/2526/00227 RJPSL/BO/2526/00322 RDDPL/BO/2526/00096, RDDPL/BO/2526/00110 RJPSL/BO/2526/00039, RJPSL/BO/2526/00223, RJPSL/BO/2526/00254 | Q4: RJPSL/IPO/2526/00321 RJPDD/LPO/2526/00040 RJPDD/LPO/2526/00040 RJPSL/IPO/2526/00222 RDDPL/IPO/2526/00083, RDDPL/IPO/2526/00084 RJPSL/IPO/2526/00040, RJPSL/IPO/2526/00128, RJPSL/IPO/2526/00191 | R4: Ref: Quote from WWPS
A5: 2 | B5: 325325001 | C5: Mud Pumps | D5: Main Motors(6 nos) and auxilary motors- (Overhauling) | E5: Third party | F5: 100000 | H5: =2500 -> 2500 | I5: 129935 | K5: 3941.88 | N5: =H5*0.27+I5+J5*0.01149+K5+L5 -> 134551.88 | O5: =F5-N5 -> -34551.88 | P5: RJPSL/BO/2526/00465 RDDPL/BO/2526/00120 RJPSL/BO/2526/00038, RJPSL/BO/2526/00112, RJPSL/BO/2526/00233, RJPSL/BO/2526/00224 | Q5: RJPSL/IPO/2526/00334 RDDPL/IPO/2526/00080 RJPSL/IPO/2526/00039, RJPSL/IPO/2526/00089, RJPSL/IPO/2526/00193, RJPSL/IPO/2526/00194 | R5: Considered in Sr no 2
A6: 3 | B6: 312081001 | C6: Drawworks | D6: Main Motors-( 3nos) and auxilary motors Overhauling & DWS Brake cooling Flow issue need to rectify . | E6: Third party | H6: 10719.5 | N6: =H6*0.27+I6+J6*0.01149+K6+L6 -> 2894.265 | O6: =F6-N6 -> -2894.265 | P6: RJPSL/BO/2526/00222 | Q6: RJPSL/IPO/2526/00313 | R6: Considered in Sr no 2
A7: 4 | B7: 313314 | C7: Top Drive | D7: Main Motor & auxiliary motor - overhauling | E7: Third party | N7: =H7*0.27+I7+J7*0.01149+K7+L7 -> 0 | O7: =F7-N7 -> 0 | R7: Considered in Annexure VI Sr no 4
A8: 5 | B8: 313081011 | C8: Rotary table | D8: Main Motor & auxiliary motor - overhauling | E8: Third party | N8: =H8*0.27+I8+J8*0.01149+K8+L8 -> 0 | O8: =F8-N8 -> 0 | R8: Considered in Sr no 2
A9: 6 | B9: 311085001 | C9: Rig Sense | D9: Rig sense system need to be updated to latest version & all the sensor fault rectification and calibration by NOV. (Mud pit, trip tank level sensors, mud conductivity, density, temperature sensors and mud return flow sensor). | E9: Third party | F9: 120000 | K9: 115449.01 | N9: =H9*0.27+I9+J9*0.01149+K9+L9 -> 115449.01 | O9: =F9-N9 -> 4550.99 | P9: RDDPL/BO/2526/00128 | Q9: RDDPL/IPO/2526/00102 | R9: Ref-JE DD 25 $120000
A10: 7 | B10: 488 | C10: Jacking System | D10: Jacking system and need to carryout health check up (Motors, Brakes & Jacking MCC Panels). | E10: Third party | F10: 25000 | N10: =H10*0.27+I10+J10*0.01149+K10+L10 -> 0 | O10: =F10-N10 -> 25000 | R10: Estimated
A11: 8 | B11: 867090001 | C11: Variable frequeny Drives | D11: All the VFDs (Mud pump, Draw works and TDS/RT)need to carryout health check up . | E11: Third party | F11: 25000 | H11: =2450+2193 -> 4643 | N11: =H11*0.27+I11+J11*0.01149+K11+L11 -> 1253.61 | O11: =F11-N11 -> 23746.39 | P11: RJPSL/BO/2526/00324 RJPSL/BO/2526/00251 | Q11: RJPSL/IPO/2526/00360 RJPSL/IPO/2526/00207
A12: 9 | B12: 311084001 | C12: Amphion | D12: Amphion Integrated network system need to carryout healthcheckup and necessary trouble shooting if required | E12: Third party | F12: 25000 | N12: =H12*0.27+I12+J12*0.01149+K12+L12 -> 0 | O12: =F12-N12 -> 25000 | R12: Estimated
A13: 10 | B13: 871088/872088 | C13: Main & Emergency switchboard | D13: All the switchboard (PCR, E-Gen) main breakers health check-up and primary current injection test . | E13: Third party | F13: 25000 | H13: 1764.19 | K13: 8933 | L13: 14882 | N13: =H13*0.27+I13+J13*0.01149+K13+L13 -> 24291.331 | O13: =F13-N13 -> 708.6687 | P13: RJPSL/BO/2526/00214 RDDPL/BO/2526/00067, RDDPL/BO/2526/00129 | Q13: RJPSL/IPO/2526/00169 RDDPL/IPO/2526/00035, RDDPL/IPO/2526/00107 | R13: Estimated
A14: 11 | B14: 5710 | C14: HVAC | D14: All the HVAC, FAHU ,chiller freezer ,driller cabinunit health check-up , troubleshooting required | E14: Third party | F14: 125000 | H14: =350+180455+2700+3765+11024 -> 198294 | K14: =9940+209.2 -> 10149.2 | L14: 80926 | N14: =H14*0.27+I14+J14*0.01149+K14+L14 -> 144614.58 | O14: =F14-N14 -> -19614.58 | P14: RJPSL/BO/2526/00471 RJPSL/BO/2526/00464 RDDPL/BO/2526/00175 RJPSL/BO/2526/00301 RJPSL/BO/2526/00335 RJPSL/BO/2526/00288 | Q14: RJPSL/IPO/2627/00015 RJPSL/IPO/2526/00347 RDDPL/IPO/2526/00140 RJPSL/IPO/2526/00293 RJPSL/IPO/2526/00238 RJPSL/IPO/2526/00216 | R14: Estimated
A15: 12 | C15: Motors | D15: All the motors (Mud mixing, mud charging, fire pump motor, foam pump motor, drill floor HPU, cantilever skidding motor, Radiator motor, mud cutting dryer motor, PORT AFT & PORT FWD crane motor, shale shaker motor, Desander, Desilter, Degasser motor, Mud centrifuge motor, brake cooling motors, mud agitator motors, Air compressor motor, cement unit chemical mixing motors, Trip tank motor, All the life boat motors.) motors need to be inspect (health check-up) including Vibration Checks. | E15: Third party | F15: 100000 | H15: 14955 | K15: =4629+46994 -> 51623 | N15: =H15*0.27+I15+J15*0.01149+K15+L15 -> 55660.85 | O15: =F15-N15 -> 44339.15 | P15: RDDPL/BO/2526/00138 RJPSL/BO/2526/00196, RJPSL/BO/2526/00289 RDDPL/BO/2526/00054, RDDPL/BO/2526/00054, RDDPL/BO/2526/00090 | Q15: RDDPL/IPO/2526/00136 RJPSL/IPO/2526/00151, RJPSL/IPO/2526/00201 RDDPL/IPO/2526/00042, RDDPL/IPO/2526/00043, RDDPL/IPO/2526/00072 | R15: Estimated
A16: 13 | C16: Electrical | D16: Panel Meter calibration and certification | E16: Third party | F16: 10000 | K16: =521+412 -> 933 | N16: =H16*0.27+I16+J16*0.01149+K16+L16 -> 933 | O16: =F16-N16 -> 9067 | P16: RDDPL/BO/2526/00151 RDDPL/BO/2526/00151 | Q16: RDDPL/IPO/2526/00137 RDDPL/IPO/2526/00138 | R16: Estimated
A17: 14 | C17: Transformers | D17: 2000 KVA( 2no) AND 225 KVA(3 no) TRANSFORMER Inspection & health checkup | E17: Third party | F17: 10000 | L17: 5978 | N17: =H17*0.27+I17+J17*0.01149+K17+L17 -> 5978 | O17: =F17-N17 -> 4022 | R17: Estimated
A18: 15 | C18: Cementing unit & Batch mixer engine | D18: Data Monitoring system need to be Installed and Configure , Batch mixer engine starting issue Need to troubleshoot and rectify. | E18: Third party | F18: 40000 | N18: =H18*0.27+I18+J18*0.01149+K18+L18 -> 0 | O18: =F18-N18 -> 40000 | R18: Estimated
A19: 16 | B19: 421 | C19: Radio equipments | D19: Need to carryout health check UP & fault rectification , PROCREMENT | E19: Third party | F19: 10000 | H19: 2000 | I19: 1000 | J19: 66000 | N19: =H19*0.27+I19+J19*0.01149+K19+L19 -> 2298.34 | O19: =F19-N19 -> 7701.66 | P19: RJPDD/BO/2526/00271 RJPSL/BO/2526/00213 RJPSL/BO/2526/00036, RJPSL/BO/2526/00284 | Q19: RJPDD/LPO/2526/00056 RJPSL/IPO/2526/00256 RJPSL/IPO/2526/00037, RJPSL/IPO/2526/00189 | R19: Estimated
A20: 17 | B20: 867 | C20: Main UPS (35KVA) | D20: Main UPS need to be inspected and serviced | E20: Rig Crew | F20: 10000 | N20: =H20*0.27+I20+J20*0.01149+K20+L20 -> 0 | O20: =F20-N20 -> 10000 | R20: Estimated
A21: 18 | B21: 372056001 | C21: Burner boom | D21: Burner boom ignition system need to be serviced by inhouse and remedial spares | E21: Rig Crew | F21: 50000 | J21: 245000 | N21: =H21*0.27+I21+J21*0.01149+K21+L21 -> 2815.05 | O21: =F21-N21 -> 47184.95 | P21: RJPDD/BO/2526/00248 | Q21: RJPDD/LPO/2526/00031 | R21: Estimated
A22: 19 | B22: 332068001 | C22: BOP UPS (3.75 KVA) | D22: BOP Control unit UPS Batteries need to replace Existing batteries are expired already 07/2023. | E22: Rig Crew | F22: 10000 | H22: 3520 | N22: =H22*0.27+I22+J22*0.01149+K22+L22 -> 950.4 | O22: =F22-N22 -> 9049.6 | P22: RJPSL/BO/2526/00128 | Q22: RJPSL/IPO/2526/00108 | R22: Estimated
A23: 20 | B23: 196062002 | C23: Galley Equipments | D23: Galley equipment’s need to be inspected ( ice cube machine BER raised MR) | E23: Rig Crew | F23: 10000 | H23: =2855+4222+125 -> 7202 | N23: =H23*0.27+I23+J23*0.01149+K23+L23 -> 1944.54 | O23: =F23-N23 -> 8055.46 | P23: RJPSL/BO/2526/00255 RJPSL/BO/2526/00315 RJPSL/BO/2526/00048 | Q23: RJPSL/IPO/2526/00237 RJPSL/IPO/2526/00231 RJPSL/IPO/2526/00047 | R23: Estimated
A24: 21 | B24: 811 | C24: Fire & Gas System | D24: Fire & Gas system inspection and repair. | E24: Third party | F24: 25000 | H24: 4842 | J24: 568866 | K24: 8696 | N24: =H24*0.27+I24+J24*0.01149+K24+L24 -> 16539.61 | O24: =F24-N24 -> 8460.3897 | P24: RJPDD/BO/2526/00287 RJPSL/BO/2526/00507 RDDPL/BO/2526/00184 | Q24: RJPDD/LPO/2627/00003 RJPSL/IPO/2627/00014 RDDPL/IPO/2526/00150 | R24: Estimated
A25: 22 | B25: 425094 | C25: PAGA | D25: All the telephone inspection and repair. | E25: Third party | F25: 25000 | H25: 4604 | N25: =H25*0.27+I25+J25*0.01149+K25+L25 -> 1243.08 | O25: =F25-N25 -> 23756.92 | P25: RJPSL/BO/2526/00126 | Q25: RJPSL/IPO/2526/00114 | R25: Estimated
A26: 23 | B26: 821069001 | C26: Tank gauging system | D26: Tankgauging system PC not working in control room, need to rectify the issue. | E26: Third party | F26: 50000 | N26: =H26*0.27+I26+J26*0.01149+K26+L26 -> 0 | O26: =F26-N26 -> 50000 | R26: Estimated
A27: 24 | C27: General | D27: EX survey | E27: Third party | F27: 10000 | L27: 11090 | N27: =H27*0.27+I27+J27*0.01149+K27+L27 -> 11090 | O27: =F27-N27 -> -1090 | R27: Estimated
A28: 25 | C28: General | D28: Remedial action of EX survey | E28: Third party | F28: 30000 | H28: 1020 | K28: 1008 | N28: =H28*0.27+I28+J28*0.01149+K28+L28 -> 1283.4 | O28: =F28-N28 -> 28716.6 | P28: RDDPL/BO/2526/00171 RJPSL/BO/2526/00445 | Q28: RDDPL/IPO/2526/00147 RJPSL/IPO/2526/00344 | R28: Estimated
A29: 26 | C29: General | D29: Noise/DB survey | E29: Rig Crew | N29: =H29*0.27+I29+J29*0.01149+K29+L29 -> 0 | O29: =F29-N29 -> 0 | R29: Estimated
A30: 27 | C30: General | D30: Thermographic survey | E30: Rig Crew | N30: =H30*0.27+I30+J30*0.01149+K30+L30 -> 0 | O30: =F30-N30 -> 0 | R30: Estimated
A31: 28 | C31: General | D31: Lux Survey | E31: Rig Crew | N31: =H31*0.27+I31+J31*0.01149+K31+L31 -> 0 | O31: =F31-N31 -> 0 | R31: Estimated
A32: 29 | B32: 892085001 | C32: General | D32: General Rig lighting improvement | E32: Rig crew | F32: 100000 | H32: =18371+1908 -> 20279 | K32: =52231.3+3665+12065 -> 67961.3 | N32: =H32*0.27+I32+J32*0.01149+K32+L32 -> 73436.63 | O32: =F32-N32 -> 26563.37 | P32: RJPSL/BO/2526/00447 RDDPL/BO/2526/00142 RDDPL/BO/2526/00135 RJPSL/BO/2526/00084, RJPSL/BO/2526/00229, RJPSL/BO/2526/00212, RJPSL/BO/2526/00212 | Q32: RJPSL/IPO/2526/00358 RDDPL/IPO/2526/00125 RDDPL/IPO/2526/00104 RJPSL/IPO/2526/00077, RJPSL/IPO/2526/00138, RJPSL/IPO/2526/00160, RJPSL/IPO/2526/00162 | R32: Ref- JS DD -23 $100000
A33: 30 | B33: 4270 | C33: General | D33: Aviation warning lights, Navigation lights/Battery/ Replacement and remedial if required | E33: Rig crew/Third party | F33: 10000 | H33: 12060 | I33: 456.68 | J33: 40500 | K33: 2916.81 | N33: =H33*0.27+I33+J33*0.01149+K33+L33 -> 7095.035 | O33: =F33-N33 -> 2904.965 | P33: RJPDD/BO/2526/00079 RDDPL/BO/2526/00094 RJPSL/BO/2526/00089, RJPSL/BO/2526/00239 | Q33: RJPDD/LPO/2526/00003 RDDPL/IPO/2526/00091 RJPSL/IPO/2526/00079, RJPSL/IPO/2526/00080, RJPSL/IPO/2526/00155 | R33: Estimated
A34: 31 | C34: General | D34: Emergency lighting | E34: Rig crew | F34: 25000 | N34: =H34*0.27+I34+J34*0.01149+K34+L34 -> 0 | O34: =F34-N34 -> 25000 | R34: Estimated
A35: 32 | C35: General | D35: Electrical Tools, calibration of potable electric meters | E35: Third party | F35: 50000 | H35: =1411.7+3145.29+23010+605.52+1100+635.89+1891.55+11294+9450 -> 52543.95 | N35: =H35*0.27+I35+J35*0.01149+K35+L35 -> 14186.867 | O35: =F35-N35 -> 35813.133 | P35: RJPSL/BO/2526/00384 RJPSL/BO/2526/00006, RJPSL/BO/2526/00006, RJPSL/BO/2526/00015, RJPSL/BO/2526/00021, RJPSL/BO/2526/00219, RJPSL/BO/2526/00219, RJPSL/BO/2526/00218, RJPSL/BO/2526/00217 | Q35: RJPSL/IPO/2526/00258 RJPSL/IPO/2526/00006, RJPSL/IPO/2526/00008, RJPSL/IPO/2526/00020, RJPSL/IPO/2526/00024, RJPSL/IPO/2526/00158, RJPSL/IPO/2526/00159, RJPSL/IPO/2526/00186, RJPSL/IPO/2526/00190 | R35: Estimated
A36: 33 | B36: 196062004 | C36: Electrical | D36: Cables/Fittings/Consumbales | F36: 50000 | H36: =28649+10327+2000+8575+1000+7227+425 -> 58203 | J36: 85350 | K36: 5117.5 | N36: =H36*0.27+I36+J36*0.01149+K36+L36 -> 21812.982 | O36: =F36-N36 -> 28187.018 | P36: RJPSL/BO/2526/00449 RJPSL/BO/2526/00474 RJPDD/BO/2526/00288 RJPSL/BO/2526/00446 RJPSL/BO/2526/00256 RJPSL/BO/2526/00257 RJPSL/BO/2526/00256 RDDPL/BO/2526/00100 RJPSL/BO/2526/00008, RJPSL/BO/2526/00023, RJPSL/BO/2526/00044, RJPSL/BO/2526/00174, RJPSL/BO/2526/00226, RJPSL/BO/2526/00243, RJPSL/BO/2526/00256, RJPSL/BO/2526/00249, RJPSL/BO/2526/00248, RJPSL/BO/2526/00261, RJPSL/BO/2526/00310 | Q36: RJPSL/IPO/2627/00007 RJPSL/IPO/2526/00357 RJPDD/LPO/2526/00059 RJPSL/IPO/2526/00318 RJPSL/IPO/2526/00276 RJPSL/IPO/2526/00261 RJPSL/IPO/2526/00229 RDDPL/IPO/2526/00056 RJPSL/IPO/2526/00009, RJPSL/IPO/2526/00027, RJPSL/IPO/2526/00045, RJPSL/IPO/2526/00099, RJPSL/IPO/2526/00107, RJPSL/IPO/2526/00164, RJPSL/IPO/2526/00168, RJPSL/IPO/2526/00179, RJPSL/IPO/2526/00182, RJPSL/IPO/2526/00185, RJPSL/IPO/2526/00211, RJPSL/IPO/2526/00212 | R36: Estimated
A37: 34 | C37: Electrical | D37: Third party SME/Extra electrical pax | E37: Third party | F37: 25000 | H37: 4703 | N37: =H37*0.27+I37+J37*0.01149+K37+L37 -> 1269.81 | O37: =F37-N37 -> 23730.19 | P37: RJPSL/BO/2526/00176 | Q37: RJPSL/IPO/2526/00362 | R37: Estimated
A38: 35 | C38: Ventillation fan motors | D38: Overhauling and balancing of supply and exhaust fan motors | E38: Third party | F38: 25000 | N38: =H38*0.27+I38+J38*0.01149+K38+L38 -> 0 | O38: =F38-N38 -> 25000 | R38: Estimated
A39: 36 | C39: IMMCS | D39: HMI station work function, Communication error, UPS function test Troubleshooting and Remedial | E39: Rig crew/Third party | F39: 100000 | H39: =7000+19700+8465 -> 35165 | N39: =H39*0.27+I39+J39*0.01149+K39+L39 -> 9494.55 | O39: =F39-N39 -> 90505.45 | P39: RJPSL/BO/2526/00463 RJPSL/BO/2526/00129 RJPSL/BO/2526/00244 | Q39: RJPSL/IPO/2526/00332 RJPSL/IPO/2526/00105 RJPSL/IPO/2526/00219 | R39: Estimated
A40: 37 | C40: General | D40: Cable trays repair job | E40: Rig crew/Third party | F40: 50000 | L40: 12790 | N40: =H40*0.27+I40+J40*0.01149+K40+L40 -> 12790 | O40: =F40-N40 -> 37210 | P40: RJPDD/BO/2526/00230 | R40: Estimated
A41: Total | F41: =SUM(F4:F40) -> 1320000 | G41: =SUM(G4:G40) -> 4350000 | N41: =SUM(N4:N40) -> 712385.22 | O41: =F41-N41 -> 607614.78

Sheet Ann IX-Marine
A1: BUDGETED EXPENSES FOR JINDAL PIONEER RECERTIFICATION & MISCELLANEOUS SERVICES - ANNEXURE IX
A2: I | C2: Lifting gear, Marine and Safety
A3: Sr. No. | C3: Area | D3: DEPARTMENT / JOB DESCRIPTION | E3: WORK TO BE DONE BY | F3: Budgetory Cost (USD) | G3: BUDGETORY COST (INR) | H3: Actual Local Cost (AED) | I3: Actual Local Cost (USD) | J3: Actual Local Cost (INR) | K3: Total Cost IMPORT (USD) | L3: VOR (USD) | M3: Projected Cost | N3: Actucal Total Cost (USD) | O3: Surplus/Exceeded | P3: MR NO | Q3: PO NO | R3: Remarks | S3: CS VALUE TILL DATE
A4: 1 | C4: Misc/General | D4: PRVs/PSVs, Weight indicators, Load cells & Gauges(Pressure ,Temp, Compound, SPM, Differential Pressure,Vaccum, Tong Torque,RPM), Pressure switch, Crane Load indicator, Pressure Transmitter) - Calibration & Remedial | E4: Third Party | F4: 50000 | G4: =F4*87 -> 4350000 | H4: =9225+5838 -> 15063 | L4: 15219 | N4: =H4*0.27+I4+J4*0.01149+K4+L4 -> 19286.01 | O4: =F4-N4 -> 30713.99 | P4: RJPSL/BO/2526/00432 RJPSL/BO/2526/00359 | Q4: RJPSL/IPO/2526/00315 RJPSL/IPO/2526/00264 | R4: Estimated
A5: 2 | C5: Misc/General | D5: Base oil need to install flow meter on both loading station (digital) & Calibration of Flowmeter - Pot Water, Drill water, Fuel | E5: Third Party | F5: 25000 | G5: =F5*87 -> 2175000 | N5: =H5*0.27+I5+J5*0.01149+K5+L5 -> 0 | O5: =F5-N5 -> 25000 | R5: Estimated
A6: 3 | C6: Misc/General | D6: Pressure Vessels UTG ( Air receiver @ Main Engine Room, Rig Floor, EMG Gen, Cold Start Comp, Air storage at BOP control unit, cement, Surge Tank, Batch Mixer Tank & Barite Tank) & Hydrotesting | E6: Third Party | F6: 10000 | G6: =F6*87 -> 870000 | H6: 14896 | J6: 225000 | N6: =H6*0.27+I6+J6*0.01149+K6+L6 -> 6607.17 | O6: =F6-N6 -> 3392.83 | P6: RJPDD/BO/2526/00243 RJPSL/BO/2526/00294 | Q6: RJPDD/LPO/2526/00027 RJPSL/IPO/2526/00210 | R6: Estimated
A7: 4 | C7: Misc/General | D7: Lifting gear Inspection including Towing tackles - Main & Emergency, TDS hang off line, Lifting tackles for BOP, Pile hammer & Burner Boom | E7: Third Party | F7: 25000 | G7: =F7*87 -> 2175000 | H7: 14700 | L7: 19580 | N7: =H7*0.27+I7+J7*0.01149+K7+L7 -> 23549 | O7: =F7-N7 -> 1451 | P7: RJPSL/BO/2526/00365 | Q7: RJPSL/IPO/2526/00257 | R7: Estimated
A8: 5 | C8: Misc/General | D8: Remedial of Lifting Gear Inspection | E8: Third Party | F8: 100000 | G8: =F8*87 -> 8700000 | H8: 6437.49 | N8: =H8*0.27+I8+J8*0.01149+K8+L8 -> 1738.1223 | O8: =F8-N8 -> 98261.878 | P8: RJPSL/BO/2526/00250 | Q8: RJPSL/IPO/2526/00178 | R8: Estimated
A9: 6 | B9: 434 | C9: Misc/General | D9: General NDT of Load bearing foundation - All Winches foundation including ,Anchor, fairleads, Towing Fixed tackles-Smith Bracket & Bridle,Chaffing Chain, Delta Plate, Bop Hoist Chain, Helideck, Jackhouse structure | E9: Third Party | F9: 50000 | G9: =F9*87 -> 4350000 | H9: 220 | N9: =H9*0.27+I9+J9*0.01149+K9+L9 -> 59.4 | O9: =F9-N9 -> 49940.6 | P9: RJPSL/BO/2526/00055 | Q9: RJPSL/IPO/2526/00051 | R9: Estimated
D10: Anchor winch refurbishment | F10: 25000 | G10: =F10*87 -> 2175000 | N10: =H10*0.27+I10+J10*0.01149+K10+L10 -> 0 | O10: =F10-N10 -> 25000 | R10: Estimated
A11: 7 | C11: Misc/General | D11: UTG of LP Pipe lines - SW, Pot, DW, FO, Bulk line@manifold,Cement& Barite & LP mud line, Rig Air, Engine Exhaust, Fire Line | E11: Third Party | F11: 10000 | G11: =F11*87 -> 870000 | N11: =H11*0.27+I11+J11*0.01149+K11+L11 -> 0 | O11: =F11-N11 -> 10000 | R11: Estimated
A12: 8 | C12: Misc/General | D12: UTG of HP Pipe lines- Well test(Burner line-Oil/Gas)BOP control/Standpipe/Mud/Choke& Kill/Cement/ | E12: Third Party | F12: 10000 | G12: =F12*87 -> 870000 | N12: =H12*0.27+I12+J12*0.01149+K12+L12 -> 0 | O12: =F12-N12 -> 10000 | R12: Estimated
A13: 9 | C13: Statutary/Regulatory | D13: UTG of Ballast /Void/Mud/Diesel/Pot/DW Tanks/Base Oil wherewever applicable | E13: Third Party | F13: 10000 | G13: =F13*87 -> 870000 | N13: =H13*0.27+I13+J13*0.01149+K13+L13 -> 0 | O13: =F13-N13 -> 10000 | R13: Estimated
A14: 10 | C14: Jetting | D14: Leg Jetting System inhouse inspection and maintanence | E14: Rig crew | F14: 10000 | G14: =F14*87 -> 870000 | N14: =H14*0.27+I14+J14*0.01149+K14+L14 -> 0 | O14: =F14-N14 -> 10000 | R14: Estimated
A15: 11 | C15: Cranes | D15: Cranes -Annual Inspection, cabin glass change, boom srtucture painting, and minor cabin repair jobs. | E15: Third Party | F15: 400000 | G15: =F15*87 -> 34800000 | H15: =13656+10000 -> 23656 | I15: =6984+12000+4200 -> 23184 | N15: =H15*0.27+I15+J15*0.01149+K15+L15 -> 29571.12 | O15: =F15-N15 -> 370428.88 | P15: RJPSL/BO/2526/00466 RJPSL/BO/2526/00425 RJPSL/BO/2526/00061 RJPSL/BO/2526/00221 | Q15: RJPSL/IPO/2627/00005 RJPSL/IPO/2526/00314 RJPSL/IPO/2526/00053 RJPSL/IPO/2526/00054 RJPSL/IPO/2526/00200 | R15: Estimated
A16: 12 | C16: Cranes | D16: Remedial against crane inspection | E16: Third Party | G16: =F16*87 -> 0 | N16: =H16*0.27+I16+J16*0.01149+K16+L16 -> 0 | R16: Considred in Sr. NO 11
A17: 13 | C17: Cranes | D17: Pre & Post NDT of Collum,Boom structures, Load bearing Components | E17: Third Party | G17: =F17*87 -> 0 | N17: =H17*0.27+I17+J17*0.01149+K17+L17 -> 0 | R17: Considred in Sr. NO 11
A18: 14 | C18: Cranes | D18: Boom Wire, Pendent & Block wire change out | E18: Rig Crew | G18: =F18*87 -> 0 | N18: =H18*0.27+I18+J18*0.01149+K18+L18 -> 0 | R18: Considred in Sr. NO 11
A19: 15 | C19: Cranes | D19: Load Test of Crane | E19: Third Party | G19: =F19*87 -> 0 | N19: =H19*0.27+I19+J19*0.01149+K19+L19 -> 0 | R19: Considred in Sr. NO 11
A20: 16 | C20: Cranes | D20: Remedial of Crane DROP survey | E20: Third Party | G20: =F20*87 -> 0 | N20: =H20*0.27+I20+J20*0.01149+K20+L20 -> 0 | R20: Considred in Sr. NO 11
A21: 17 | C21: lIfting | D21: Derrick Escape Device - Recertification | E21: Third Party | F21: 10000 | G21: =F21*87 -> 870000 | J21: 561763 | N21: =H21*0.27+I21+J21*0.01149+K21+L21 -> 6454.6569 | O21: =F21-N21 -> 3545.3431 | P21: RJPDD/BO/2526/00269 | Q21: RJPDD/LPO/2526/00045 | R21: Estimated
A22: 18 | C22: lIfting | D22: Load test - CSB, Utility winches, Derrick Winch, Manrider Winches, BOP Hoist | E22: Third Party | F22: 10000 | G22: =F22*87 -> 870000 | H22: 6630 | N22: =H22*0.27+I22+J22*0.01149+K22+L22 -> 1790.1 | O22: =F22-N22 -> 8209.9 | P22: RJPSL/BO/2526/00098 | Q22: RJPSL/IPO/2526/00083 | R22: Estimated
A23: 19 | C23: PTB | D23: New purchase- 2PTB | F23: 48000 | G23: =F23*87 -> 4176000 | K23: 49944 | N23: =H23*0.27+I23+J23*0.01149+K23+L23 -> 49944 | O23: =F23-N23 -> -1944 | P23: RDDPL/BO/2526/00053, RDDPL/BO/2526/00015 | Q23: RDDPL/IPO/2526/00001, RDDPL/IPO/2526/00051 | R23: Ref SUPDD 2024 - $48000
A24: 20 | C24: Helideck | D24: Foam monitors and sprinkler system | E24: Third Party | F24: 15000 | G24: =F24*87 -> 1305000 | H24: 15133 | N24: =H24*0.27+I24+J24*0.01149+K24+L24 -> 4085.91 | O24: =F24-N24 -> 10914.09 | P24: RJPSL/BO/2526/00317 | Q24: RJPSL/IPO/2526/00240 | R24: Estimated
A25: 21 | C25: Helideck | D25: Load test of perimeter net | E25: Third Party | F25: 5000 | G25: =F25*87 -> 435000 | L25: =3562+2222 -> 5784 | N25: =H25*0.27+I25+J25*0.01149+K25+L25 -> 5784 | O25: =F25-N25 -> -784 | R25: Estimated
A26: 22 | C26: Helideck | D26: Procurement of Helideck net | E26: Third Party | F26: 3000 | G26: =F26*87 -> 261000 | H26: 2480 | J26: 183942.01 | N26: =H26*0.27+I26+J26*0.01149+K26+L26 -> 2783.0937 | O26: =F26-N26 -> 216.90631 | P26: RJPDD/BO/2526/00241 RJPSL/BO/2526/00197 | Q26: RJPDD/LPO/2526/00033 RJPSL/IPO/2526/00173 | R26: Estimated $3000
A27: 23 | C27: Skidding | D27: Cantilever skidding unit-overhaul | E27: Third Party | F27: 50000 | G27: =F27*87 -> 4350000 | I27: 3942 | N27: =H27*0.27+I27+J27*0.01149+K27+L27 -> 3942 | O27: =F27-N27 -> 46058 | R27: Estimated
A28: 24 | C28: Fixation System | D28: Replace bolt of Fixation system | E28: Third Party | G28: =F28*87 -> 0 | N28: =H28*0.27+I28+J28*0.01149+K28+L28 -> 0
A29: 25 | C29: Safety | D29: FSA/LSA annual inspection - Fire detection system , hydrants, hoses, extingusishers ,Oxygen Cylinders, LB Air cylinders, Pyrotechnic, BUOY, SCBA, Fire Station, Portable system - Annual Inspection and remedial | E29: Third Party | F29: 75000 | G29: =F29*87 -> 6525000 | H29: =89777+30982+4112+1350 -> 126221 | I29: =1100 -> 1100 | J29: =12300+6444 -> 18744 | K29: 3825 | N29: =H29*0.27+I29+J29*0.01149+K29+L29 -> 39220.039 | O29: =F29-N29 -> 35779.961 | P29: RJPDD/BO/2526/00265 RJPDD/BO/2526/00128 RJPSL/BO/2526/00357 RJPSL/BO/2526/00354 RJPSL/BO/2526/00321 RJPSL/BO/2526/00050, RJPSL/BO/2526/00053, RJPSL/BO/2526/00072, RJPSL/BO/2526/00074, RJPSL/BO/2526/00081, RJPSL/BO/2526/00062, RJPSL/BO/2526/00215, RJPSL/BO/2526/00062 RDDPL/BO/2526/00099 | Q29: RJPDD/LPO/2526/00050 RJPDD/LPO/2526/00049 RJPSL/IPO/2526/00309 RJPSL/IPO/2526/00251 RJPSL/IPO/2526/00224 RJPSL/IPO/2526/00049, RJPSL/IPO/2526/00050, RJPSL/IPO/2526/00062, RJPSL/IPO/2526/00064, RJPSL/IPO/2526/00068, RJPSL/IPO/2526/00102, RJPSL/IPO/2526/00141, RJPSL/IPO/2526/00170 RDDPL/IPO/2526/00055 | R29: Estimated
A30: 26 | C30: Safety | D30: Fire Fighting System- C02 Fixed @ Engine Room, Paint Locker, E-Gen , SCR - Inspection & Recertification . Bottle Pressure Testing as required based on due date. | E30: Third Party | F30: 50000 | G30: =F30*87 -> 4350000 | H30: =26716+48571+12580+145.8+2943+4111+2565 -> 97631.8 | J30: 36100 | N30: =H30*0.27+I30+J30*0.01149+K30+L30 -> 26775.375 | O30: =F30-N30 -> 23224.625 | P30: RJPDD/BO/2526/00110 RJPSL/BO/2526/00421 RJPSL/BO/2526/00444 RJPSL/IPO/2526/00239 RJPSL/BO/2526/00272 RJPSL/BO/2526/00031, RJPSL/BO/2526/00049 | Q30: RJPDD/LPO/2526/00051 RJPSL/IPO/2526/00312 RJPSL/IPO/2526/00290 RJPSL/BO/2526/00264 RJPSL/IPO/2526/00233 RJPSL/IPO/2526/00034, RJPSL/IPO/2526/00048 | R30: Estimated
A31: 27 | C31: Safety | D31: Remedial Against LSA/FSA- replacement of fixed CO2 system Hoses | E31: Third Party | G31: =F31*87 -> 0 | N31: =H31*0.27+I31+J31*0.01149+K31+L31 -> 0 | O31: =F31-N31 -> 0 | P31: RJPSL/BO/2526/00091 | Q31: RJPSL/IPO/2526/00167 | R31: Considered in Sr no 25
A32: 28 | C32: Safety | D32: Hydrotest of Lifeboat Air cylinders, Fixed CO2 Cyinders, EBBD, SCBA | E32: Third Party | G32: =F32*87 -> 0 | H32: 4016 | N32: =H32*0.27+I32+J32*0.01149+K32+L32 -> 1084.32 | R32: Considered in Sr no 25
A33: 29 | C33: Safety | D33: Fire Dampner @Machinary room, Mud pump, Engine room and accommodation to be inspected | E33: Third Party | G33: =F33*87 -> 0 | N33: =H33*0.27+I33+J33*0.01149+K33+L33 -> 0 | R33: Considered in Sr no 26
A34: 30 | B34: 816 | C34: Safety | D34: Helideck foam system - Annual inspection, AFFF 3% foam test | E34: Third Party | G34: =F34*87 -> 0 | N34: =H34*0.27+I34+J34*0.01149+K34+L34 -> 0 | R34: Considered in Sr no 26
A35: 31 | B35: 816 | C35: Safety | D35: Water Deluge system/Wet Chemical - annual inspection | E35: Third Party | G35: =F35*87 -> 0 | N35: =H35*0.27+I35+J35*0.01149+K35+L35 -> 0 | R35: Considered in Sr no 26
A36: 32 | B36: 50106 | C36: Safety | D36: Annual inspection of Port & STBD lifeboats, FRC and its davit | E36: Third Party | F36: 50000 | G36: =F36*87 -> 4350000 | H36: =1635+1316+31589+120+530 -> 35190 | I36: =9000+5548+1529 -> 16077 | N36: =H36*0.27+I36+J36*0.01149+K36+L36 -> 25578.3 | O36: =F36-N36 -> 24421.7 | P36: RJPSL/BO/2526/00424 RJPSL/BO/2526/00285 RJPSL/BO/2526/00352 RJPSL/BO/2526/00252 | Q36: RJPSL/IPO/2526/00310 RJPSL/IPO/2526/00259 RJPSL/IPO/2526/00243 RJPSL/IPO/2526/00209 | R36: Estimated
A37: 33 | C37: Safety | D37: Remedial against annual inspection of Port & STBD lifeboar,FRC & its Davit with wire Replacement | E37: Third Party | G37: =F37*87 -> 0 | N37: =H37*0.27+I37+J37*0.01149+K37+L37 -> 0 | O37: =F37-N37 -> 0 | P37: RJPSL/BO/2526/00201 RJPSL/BO/2526/00366 | Q37: RJPSL/IPO/2526/00248 RJPSL/IPO/2526/00165 | R37: Considered in Sr no 32
A38: 34 | C38: Safety | D38: Lifeboat/FRC/liferaft Davits -pre & post NDT with Load test & Brake release test | E38: Third Party | G38: =F38*87 -> 0 | N38: =H38*0.27+I38+J38*0.01149+K38+L38 -> 0 | O38: =F38-N38 -> 0 | P38: RJPSL/BO/2526/00013 | Q38: RJPSL/IPO/2526/00015 | R38: Considered in Sr no 32
A39: 35 | C39: Safety | D39: Life Rafts - Recertification & replacement | E39: Third Party | G39: =F39*87 -> 0 | N39: =H39*0.27+I39+J39*0.01149+K39+L39 -> 0 | O39: =F39-N39 -> 0 | P39: RJPSL/BO/2526/00075, RJPSL/BO/2526/00106, RJPSL/BO/2526/00012 | Q39: RJPSL/IPO/2526/00065, RJPSL/IPO/2526/00085, RJPSL/IPO/2526/00117 | R39: Considered in Sr no 32
A40: 36 | C40: Safety | D40: Other Safety equipment(LADSAF, SALA Blocks,Harness,Signages etc) as per rig list - certify/repair/replace | E40: Third Party | F40: 25000 | G40: =F40*87 -> 2175000 | J40: =1271136+165482 -> 1436618 | K40: 16399.7 | N40: =H40*0.27+I40+J40*0.01149+K40+L40 -> 32906.441 | O40: =F40-N40 -> -7906.4408 | P40: RJPDD/BO/2526/00153 RJPDD/BO/2526/00118 RDDPL/BO/2526/00066 | Q40: RJPDD/LPO/2526/00008 RJPDD/LPO/2526/00014 RDDPL/IPO/2526/00059 | R40: Estimated
A41: 37 | C41: Deck equipment | D41: Preload System - Preload pump, Dump Valves, Check Valves, Replace Docking Plugs, Sounding pipes | E41: Rig crew | F41: 50000 | G41: =F41*87 -> 4350000 | H41: 2430 | N41: =H41*0.27+I41+J41*0.01149+K41+L41 -> 656.1 | O41: =F41-N41 -> 49343.9 | P41: RJPSL/BO/2526/00303 RDDPL/BO/2526/00132 | Q41: RJPSL/IPO/2526/00250 | R41: Estimated
A42: 38 | C42: Deck equipment | D42: Bray Valves | E42: Rig crew | F42: 15000 | G42: =F42*87 -> 1305000 | N42: =H42*0.27+I42+J42*0.01149+K42+L42 -> 0 | O42: =F42-N42 -> 15000 | R42: Estimated
A43: 39 | C43: Bulk Loading Station | D43: Offshore loading system - Manifold & Hoses. Port water - 2 nos x 3"; Drill Water - 2 nos x 3";Diesel - 2 nos x 3" ; Mud - 4 nos x 5" ; Cement - 2 nos x 5" ;Brine - 2 nos x 3" . Hammer Union end connection on the manifold to be checked with Secondary restraints for the hoses.Accounted in Hose Register | E43: Rig crew | F43: 50000 | G43: =F43*87 -> 4350000 | H43: 5028 | I43: =4022+25753 -> 29775 | N43: =H43*0.27+I43+J43*0.01149+K43+L43 -> 31132.56 | O43: =F43-N43 -> 18867.44 | P43: RJPSL/BO/2526/00296 RJPSL/BO/2526/00077, RJPSL/BO/2526/00078 | Q43: RJPSL/IPO/2526/00288 RJPSL/IPO/2526/00130, RJPSL/IPO/2526/00192 | R43: Estimated
A44: 40 | B44: 515 | C44: Accomodation | D44: Broken Door locks and windows replacement | E44: Rig crew/third party | F44: 150000 | G44: =F44*87 -> 13050000 | H44: =575+9071+14000 -> 23646 | L44: 22740 | N44: =H44*0.27+I44+J44*0.01149+K44+L44 -> 29124.42 | O44: =F44-N44 -> 120875.58 | P44: RJPSL/BO/2526/00457 | Q44: RJPSL/IPO/2526/00338 | R44: Estimated
A45: 41 | C45: Accommodation | D45: Repair lockers, toilet repair and remedial accessories ,(Pest control) | E45: Third Party | G45: =F45*87 -> 0 | N45: =H45*0.27+I45+J45*0.01149+K45+L45 -> 0 | O45: =F45-N45 -> 0 | P45: RJPSL/BO/2526/00320 RJPSL/BO/2526/00114 | Q45: RJPSL/IPO/2526/00304 RJPSL/IPO/2526/00090 | R45: Considered in Sr no 40
A46: 42 | C46: Galley | D46: Galley Exhaust Cleaning | E46: Third Party | G46: =F46*87 -> 0 | N46: =H46*0.27+I46+J46*0.01149+K46+L46 -> 0 | R46: Considered in Sr no 40
A47: 43 | C47: General | D47: Ducting, Insulation & Laggings | E47: Third Party | G47: =F47*87 -> 0 | N47: =H47*0.27+I47+J47*0.01149+K47+L47 -> 0 | R47: Considered in Sr no 40
A48: 44 | C48: General | D48: General maintanence and painting jobs at main and machinery deck and tanks, Hull, Scaffolding | E48: Rig Crew | F48: 100000 | G48: =F48*87 -> 8700000 | H48: =24018+400+5350+960+338+9918+2985+13912+795+92+28536+570 -> 87874 | N48: =H48*0.27+I48+J48*0.01149+K48+L48 -> 23725.98 | O48: =F48-N48 -> 76274.02 | P48: RJPSL/BO/2526/00397, RJPSL/BO/2526/00490, RJPSL/BO/2526/00377 RJPSL/BO/2526/00420 RJPSL/BO/2526/00420, RJPSL/BO/2526/00313 RJPSL/BO/2526/00390 RJPSL/BO/2526/00347 RJPSL/BO/2526/00328 RJPSL/BO/2526/00348 RJPSL/BO/2526/00034, RJPSL/BO/2526/00119, RJPSL/BO/2526/00268, RJPSL/BO/2526/00191 | Q48: RJPSL/IPO/2627/00001, RJPSL/IPO/2627/00003, RJPSL/IPO/2627/00004 RJPSL/IPO/2526/00346 RJPSL/IPO/2526/00302, RJPSL/IPO/2526/00303 RJPSL/IPO/2526/00279, RJPSL/IPO/2526/00280, RJPSL/IPO/2526/00281 RJPSL/IPO/2526/00270 RJPSL/IPO/2526/00246 RJPSL/IPO/2526/00236 RJPSL/IPO/2526/00230 RJPSL/IPO/2526/00036, RJPSL/IPO/2526/00094, RJPSL/IPO/2526/00172, RJPSL/IPO/2526/00199 | R48: Estimated
A49: 45 | C49: General | D49: Marine system Valves replacement if leaked/damaged | E49: Rig Crew | F49: 15000 | G49: =F49*87 -> 1305000 | H49: 6300 | J49: 265000 | N49: =H49*0.27+I49+J49*0.01149+K49+L49 -> 4745.85 | O49: =F49-N49 -> 10254.15 | P49: RJPSL/BO/2526/00393 RJPDD/BO/2526/00250 | Q49: RJPSL/IPO/2526/00274 RJPDD/LPO/2526/00043 | R49: Estimated
A50: 46 | C50: General | D50: Spud can Inhibitor procurement | F50: 500 | G50: =F50*87 -> 43500 | N50: =H50*0.27+I50+J50*0.01149+K50+L50 -> 0 | O50: =F50-N50 -> 500
A51: 47 | C51: General | D51: General Piping work - Low pressure- (Pipes and valves) | E51: Rig crew/third party | F51: 100000 | G51: =F51*87 -> 8700000 | H51: =4000+9043+31777+1687.4 -> 46507.4 | L51: 336464 | N51: =H51*0.27+I51+J51*0.01149+K51+L51 -> 349021 | O51: =F51-N51 -> -249021 | P51: RJPSL/BO/2526/00500 RJPSL/BO/2526/00495 RJPSL/BO/2526/00417 RJPSL/BO/2526/00364 | Q51: RJPSL/IPO/2627/00016 RJPSL/IPO/2526/00351 RJPSL/IPO/2526/00333 RJPSL/IPO/2526/00301 | R51: HP & LP pipe needs renewal as corrossion observed. 4000 M pipe line renewal estimated.
A52: 48 | C52: General | D52: General High pressure piping- (Pipes and valves) | E52: Rig crew/third party | G52: =F52*87 -> 0 | N52: =H52*0.27+I52+J52*0.01149+K52+L52 -> 0 | P52: RJPSL/BO/2526/00364 | Q52: RJPSL/IPO/2526/00301 | R52: Considered In Sr no 47
A53: 49 | C53: General | D53: Tank Cleaning/ FUEL TANSK BASE OIL TANK /PLT | E53: Rig crew/Third Party | F53: 10000 | G53: =F53*87 -> 870000 | H53: 28530 | N53: =H53*0.27+I53+J53*0.01149+K53+L53 -> 7703.1 | O53: =F53-N53 -> 2296.9 | R53: Estimated
A54: 50 | C54: General | D54: General steel work and grating work | E54: Third party | F54: 100000 | G54: =F54*87 -> 8700000 | H54: =9458.77+4125 -> 13583.77 | L54: 151500 | N54: =H54*0.27+I54+J54*0.01149+K54+L54 -> 155167.62 | O54: =F54-N54 -> -55167.618 | P54: RJPSL/BO/2526/00405 RJPSL/BO/2526/00298 | Q54: RJPSL/IPO/2526/00299 RJPSL/IPO/2526/00227 | R54: Main deck/Cantilever pipe rack deck corrossion observed. Centrifuge deck also corrossion observed. 30-40 MT estimated steel work.
A55: 51 | C55: General | D55: PPE and Adminsitration Liberia and UAE flag | F55: 20000 | G55: =F55*87 -> 1740000 | H55: =25160+250.8+41.8+4925+1304+24304+10231+660+14101+4730+450 -> 86157.6 | J55: 36480 | N55: =H55*0.27+I55+J55*0.01149+K55+L55 -> 23681.707 | O55: =F55-N55 -> -3681.7072 | P55: RJPDD/BO/2526/00256 RJPSL/BO/2526/00307 RJPSL/BO/2526/00002, RJPSL/BO/2526/00003, RJPSL/BO/2526/00004, RJPSL/BO/2526/00005, RJPSL/BO/2526/00010, RJPSL/BO/2526/00011, RJPSL/BO/2526/00011, RJPSL/BO/2526/00011, RJPSL/BO/2526/00236, RJPSL/BO/2526/00270 | Q55: RJPDD/LPO/2526/00035 RJPSL/IPO/2526/00221 RJPSL/IPO/2526/00002, RJPSL/IPO/2526/00003, RJPSL/IPO/2526/00004, RJPSL/IPO/2526/00005, RJPSL/IPO/2526/00011, RJPSL/IPO/2526/00012, RJPSL/IPO/2526/00013, RJPSL/IPO/2526/00014, RJPSL/IPO/2526/00145, RJPSL/IPO/2526/00213 | R55: Estimated | S55: 88
A56: 52 | B56: 372056001 | C56: Flare boom | D56: Burners and Burner Booms maintanence | E56: Third Party | F56: 50000 | G56: =F56*87 -> 4350000 | H56: =21998+21647 -> 43645 | I56: =14000+27555 -> 41555 | N56: =H56*0.27+I56+J56*0.01149+K56+L56 -> 53339.15 | O56: =F56-N56 -> -3339.15 | P56: RJPSL/BO/2526/00486 RJPSL/BO/2526/00487 RJPSL/BO/2526/00356 RJPSL/BO/2526/00245 | Q56: RJPSL/IPO/2526/00348 RJPSL/IPO/2526/00342 RJPSL/IPO/2526/00285 RJPSL/IPO/2526/00153 | R56: Estimated
A57: 53 | C57: General | D57: Office consumables | F57: 5000 | G57: =F57*87 -> 435000 | H57: =28530+9946 -> 38476 | N57: =H57*0.27+I57+J57*0.01149+K57+L57 -> 10388.52 | O57: =F57-N57 -> -5388.52 | P57: RJPSL/BO/2526/00370 RJPSL/BO/2526/00022, RJPSL/BO/2526/00022, RJPSL/BO/2526/00090, RJPSL/BO/2526/00094, RJPSL/BO/2526/00123, RJPSL/BO/2526/00300, RJPSL/BO/2526/00304, RJPSL/BO/2526/00276 | Q57: RJPSL/IPO/2526/00320 RJPSL/IPO/2526/00025, RJPSL/IPO/2526/00026, RJPSL/IPO/2526/00073, RJPSL/IPO/2526/00081, RJPSL/IPO/2526/00113, RJPSL/IPO/2526/00205, RJPSL/IPO/2526/00206, RJPSL/IPO/2526/00208 | R57: Estimated
A58: 54 | C58: General | D58: Barge consumables | F58: 25000 | G58: =F58*87 -> 2175000 | H58: =200546+4725+9745+7660+210 -> 222886 | K58: =9306.9+7594.7 -> 16901.6 | N58: =H58*0.27+I58+J58*0.01149+K58+L58 -> 77080.82 | O58: =F58-N58 -> -52080.82 | P58: RJPSL/BO/2526/00469 RJPSL/BO/2526/00392 RJPSL/BO/2526/00477 RJPSL/BO/2526/00413 RDDPL/BO/2526/00147 RDDPL/BO/2526/00074 RJPSL/BO/2526/00014, RJPSL/BO/2526/00014, RJPSL/BO/2526/00014, RJPSL/BO/2526/00014, RJPSL/BO/2526/00025, RJPSL/BO/2526/00025, RJPSL/BO/2526/00033, RJPSL/BO/2526/00043, RJPSL/BO/2526/00181, RJPSL/BO/2526/00240, RJPSL/BO/2526/00203, RJPSL/BO/2526/00220, RJPSL/BO/2526/00203 | Q58: RJPSL/IPO/2627/00002 RJPSL/IPO/2526/00359 RJPSL/IPO/2526/00350 RJPSL/IPO/2526/00298 RDDPL/IPO/2526/00123 RDDPL/IPO/2526/00064 RJPSL/IPO/2526/00016, RJPSL/IPO/2526/00017, RJPSL/IPO/2526/00018, RJPSL/IPO/2526/00019, RJPSL/IPO/2526/00029, RJPSL/IPO/2526/00030, RJPSL/IPO/2526/00035, RJPSL/IPO/2526/00041, RJPSL/IPO/2526/00124, RJPSL/IPO/2526/00140, RJPSL/IPO/2526/00142, RJPSL/IPO/2526/00152, RJPSL/IPO/2526/00171 | R58: Estimated
A59: 55 | C59: General | D59: Safety consumables | F59: 25000 | G59: =F59*87 -> 2175000 | H59: =41552+360+12000+231+185+1700 -> 56028 | I59: =1759.4+18079 -> 19838.4 | J59: =262300+56000+97020+157290+50715 -> 623325 | N59: =H59*0.27+I59+J59*0.01149+K59+L59 -> 42127.964 | O59: =F59-N59 -> -17127.964 | P59: RJPDD/BO/2526/00279 RJPSL/BO/2526/00394 RJPSL/BO/2526/00482 RJPDD/BO/2526/00266 RJPDD/BO/2526/00117 RJPSL/BO/2526/00438 RJPSL/BO/2526/00392 RJPSL/BO/2526/00052 RJPSL/BO/2526/00375 RJPDD/BO/2526/00050 RJPSL/BO/2526/00341 RJPDD/BO/2526/00130, RJPDD/BO/2526/00159, RJPDD/BO/2526/00164 RJPSL/BO/2526/00043, RJPSL/BO/2526/00067, RJPSL/BO/2526/00071, RJPSL/BO/2526/00073, RJPSL/BO/2526/00076, RJPSL/BO/2526/00082, RJPSL/BO/2526/00083, RJPSL/BO/2526/00087, RJPSL/BO/2526/00086, RJPSL/BO/2526/00096, RJPSL/BO/2526/00107, RJPSL/BO/2526/00200, RJPSL/BO/2526/00088, RJPSL/BO/2526/00043, RJPSL/BO/2526/00237, RJPSL/BO/2526/00287, RJPSL/BO/2526/00279 | Q59: RJPDD/LPO/2526/00061 RJPSL/IPO/2627/00006 RJPSL/IPO/2526/00355 RJPDD/LPO/2526/00055 RJPDD/LPO/2526/00048 RJPSL/IPO/2526/00308 RJPSL/IPO/2526/00306 RJPSL/IPO/2526/00294 RJPSL/IPO/2526/00282 RJPDD/LPO/2526/00046 RJPSL/IPO/2526/00232 RJPDD/LPO/2526/00006, RJPDD/LPO/2526/00019, RJPDD/LPO/2526/00020 RJPSL/IPO/2526/00044, RJPSL/IPO/2526/00059, RJPSL/IPO/2526/00061, RJPSL/IPO/2526/00063, RJPSL/IPO/2526/00066, RJPSL/IPO/2526/00069, RJPSL/IPO/2526/00070, RJPSL/IPO/2526/00071, RJPSL/IPO/2526/00072, RJPSL/IPO/2526/00082, RJPSL/IPO/2526/00086, RJPSL/IPO/2526/00125, RJPSL/IPO/2526/00127, RJPSL/IPO/2526/00136, RJPSL/IPO/2526/00156, RJPSL/IPO/2526/00176, RJPSL/IPO/2526/00204 | R59: Estimated
A60: 56 | C60: General | D60: PLT,Drill water tanks Renewal of sounding pipes as currenlty chocked | E60: Third Party/Rig crew | F60: 25000 | G60: =F60*87 -> 2175000 | H60: 1082 | N60: =H60*0.27+I60+J60*0.01149+K60+L60 -> 292.14 | O60: =F60-N60 -> 24707.86 | P60: RJPSL/BO/2526/00360 | Q60: RJPSL/IPO/2526/00242 | R60: Estimated
A61: 57 | C61: Communication | D61: Procurement of radio equipments | E61: Procurement | F61: 10000 | G61: =F61*87 -> 870000 | H61: 2052 | N61: =H61*0.27+I61+J61*0.01149+K61+L61 -> 554.04 | O61: =F61-N61 -> 9445.96 | P61: RJPSL/BO/2526/00273 | Q61: RJPSL/IPO/2526/00235 | R61: Estimated
A62: 58 | C62: Barite and Cement Silos | D62: Silos cleaning / Inspection , replace/ seal gasket of manhole hatch . Remedial if required | E62: Rig crew | F62: 10000 | G62: =F62*87 -> 870000 | N62: =H62*0.27+I62+J62*0.01149+K62+L62 -> 0 | O62: =F62-N62 -> 10000 | R62: Estimated
A63: 59 | C63: Utility Hoses | D63: Hoses procurement- water , fuel,air | E63: Procurement | F63: 10000 | G63: =F63*87 -> 870000 | H63: 7060 | I63: 1551 | N63: =H63*0.27+I63+J63*0.01149+K63+L63 -> 3457.2 | O63: =F63-N63 -> 6542.8 | P63: RJPSL/BO/2526/00462 RJPSL/BO/2526/00037 | Q63: RJPSL/IPO/2526/00361 RJPSL/IPO/2526/00038 | R63: Estimated
A64: 60 | C64: Crane | D64: Crane Stingers procurement | E64: Procurement | F64: 10000 | G64: =F64*87 -> 870000 | H64: 24012.45 | N64: =H64*0.27+I64+J64*0.01149+K64+L64 -> 6483.3615 | O64: =F64-N64 -> 3516.6385 | P64: RJPSL/BO/2526/00097 | Q64: RJPSL/IPO/2526/00106 | R64: Estimated
A65: 61 | C65: Bulk hose | D65: Bulk hose floaters | E65: Procurement | F65: 10000 | G65: =F65*87 -> 870000 | K65: 7590.87 | N65: =H65*0.27+I65+J65*0.01149+K65+L65 -> 7590.87 | O65: =F65-N65 -> 2409.13 | P65: RDDPL/BO/2526/00055 | Q65: RDDPL/IPO/2526/00034 | R65: Estimated
A66: TOTAL | F66: =SUM(F4:F65) -> 1856500 | G66: =SUM(G4:G65) -> 161515500 | N66: =SUM(N4:N65) -> 1107431.5 | O66: =F66-N66 -> 749068.54

Sheet Ann X-Contractual Req
A1: J | B1: ADDITIONAL ITEMS AS PER ONGC TENDER - ANNEXURE X
A2: S.No | B2: Equipment Description | C2: Budgetary Cost Total in USD | D2: Budgetary Cost Total in INR | E2: Actual cost Local (AED) | F2: Actual cost Local (USD) | G2: Actual cost Local (INR) | H2: Actual Cost Import (USD) | I2: Projected Cost (USD) | J2: Actucal Total Cost (USD) | K2: Surplus/Exceeded | L2: MR NO | M2: PO NO | N2: Remarks
A3: 1 | B3: Full Gauge integrated type String Stabilizers - 01 each for hole size (i) 26" (ii)17 ½”, (iii) 12 ¼”, (iv) 8 ½”, (v) 6” (Box x Pin) | C3: 18000 | D3: =C3*87 -> 1566000 | H3: 15546.96 | J3: =E3*0.27+F3+G3*0.01149+H3+I3 -> 15546.96 | K3: =C3-J3 -> 2453.04 | L3: RDDPL/BO/2526/00047 | M3: RDDPL/IPO/2526/00015 | N3: Estimated
A4: 2 | B4: Casing Spear for 7" Casing | C4: 20000 | D4: =C4*87 -> 1740000 | H4: 10896 | J4: =E4*0.27+F4+G4*0.01149+H4+I4 -> 10896 | K4: =C4-J4 -> 9104 | L4: RDDPL/BO/2526/00084, RDDPL/BO/2526/00079 | M4: RDDPL/IPO/2526/00073, RDDPL/IPO/2526/00074 | N4: Estimated
A5: 3 | B5: 9 5/8" , 7" Casing rotating scrapper activated type | C5: 14500 | D5: =C5*87 -> 1261500 | H5: 9340 | J5: =E5*0.27+F5+G5*0.01149+H5+I5 -> 9340 | K5: =C5-J5 -> 5160 | L5: RDDPL/BO/2526/00036 | M5: RDDPL/IPO/2526/00018 | N5: Estimated
A6: 4 | B6: Fishing Tools and accessories Flat bottom mill size OD 4 1/8" 3 3/8" Junk Sub | C6: 10000 | D6: =C6*87 -> 870000 | J6: =E6*0.27+F6+G6*0.01149+H6+I6 -> 0 | K6: =C6-J6 -> 10000 | L6: RDDPL/BO/2526/00083 | N6: Estimated
A7: 5 | B7: Batch Mixer: Additional Hopper arrangement | C7: 10000 | D7: =C7*87 -> 870000 | J7: =E7*0.27+F7+G7*0.01149+H7+I7 -> 0 | K7: =C7-J7 -> 10000 | N7: Estimated
A8: 6 | B8: BOP: Nut Splitter & Hydraulic Flange Spreader for BOP's and Wellheads of different sizes. | C8: 15000 | D8: =C8*87 -> 1305000 | E8: 22455 | J8: =E8*0.27+F8+G8*0.01149+H8+I8 -> 6062.85 | K8: =C8-J8 -> 8937.15 | L8: RJPSL/BO/2526/00235 | M8: RJPSL/IPO/2526/00262 | N8: Estimated
A9: 7 | B9: Hydraulic Torque Wrench | C9: 15000 | D9: =C9*87 -> 1305000 | G9: 950600 | J9: =E9*0.27+F9+G9*0.01149+H9+I9 -> 10922.394 | K9: =C9-J9 -> 4077.606 | L9: RJPDD/BO/2526/00174 | M9: RJPDD/LPO/2526/00038 | N9: Estimated
A10: 8 | B10: External Casing Cutter/Cold cutter - 9-5/8" & 13-3/8" | C10: 13000 | D10: =C10*87 -> 1131000 | G10: 992750 | J10: =E10*0.27+F10+G10*0.01149+H10+I10 -> 11406.698 | K10: =C10-J10 -> 1593.3025 | L10: RJPDD/LPO/2526/00013 | M10: RJPDD/BO/2526/00078 | N10: Estimated
A11: 9 | B11: Jet Shearing Device | C11: 60000 | D11: =C11*87 -> 5220000 | E11: 7200 | H11: 51217.45 | J11: =E11*0.27+F11+G11*0.01149+H11+I11 -> 53161.45 | K11: =C11-J11 -> 6838.55 | L11: RJPSL/BO/2526/00454 RDDPL/BO/2526/00048 | M11: RJPSL/IPO/2526/00335 RDDPL/IPO/2526/00041 | N11: Estimated
A12: 10 | B12: 2 nos Hydraulic as per API 16C | C12: 0 | D12: =C12*87 -> 0 | J12: =E12*0.27+F12+G12*0.01149+H12+I12 -> 0 | K12: =C12-J12 -> 0 | N12: Consider in Annexure VI-Sr No-24
A13: 11 | B13: Screen size of the rig sense unit display monitor in company man office should be minimum 26" | C13: 2000 | D13: =C13*87 -> 174000 | E13: 990 | J13: =E13*0.27+F13+G13*0.01149+H13+I13 -> 267.3 | K13: =C13-J13 -> 1732.7 | L13: RJPSL/BO/2526/00227 | M13: RJPSL/IPO/2526/00163 | N13: Estimated
A14: 12 | B14: 1 set of GO & NO-GO gauge for PDC & TCR bit | C14: 1149 | D14: =C14*87 -> 99963 | J14: =E14*0.27+F14+G14*0.01149+H14+I14 -> 0 | K14: =C14-J14 -> 1149 | N14: Estimated
A15: 13 | B15: Fishing Tools for 2-3/8" DP(2-3/8" Body & 3-3/8" TJ) | C15: 20000 | D15: =C15*87 -> 1740000 | J15: =E15*0.27+F15+G15*0.01149+H15+I15 -> 0 | K15: =C15-J15 -> 20000 | N15: Estimated
A16: 14 | B16: Well Bore Clenaup Tool for 9-5/8" | C16: 300000 | D16: =C16*87 -> 26100000 | H16: 83351.88 | J16: =E16*0.27+F16+G16*0.01149+H16+I16 -> 83351.88 | K16: =C16-J16 -> 216648.12 | L16: RDDPL/BO/2526/00103 | M16: RDDPL/IPO/2526/00062 | N16: Estimated
A17: 15 | B17: Test plug for all casing size | C17: 7000 | D17: =C17*87 -> 609000 | G17: 489920 | J17: =E17*0.27+F17+G17*0.01149+H17+I17 -> 5629.1808 | K17: =C17-J17 -> 1370.8192 | L17: RJPDD/BO/2526/00236 | M17: RJPDD/LPO/2526/00025 | N17: Estimated
A18: 16 | B18: String strainer | C18: 2068.9655 | D18: =C18*87 -> 180000 | J18: =E18*0.27+F18+G18*0.01149+H18+I18 -> 0 | K18: =C18-J18 -> 2068.9655 | N18: Estimated
A19: 17 | B19: 1-1/2" Tubing for annulas cleaning | C19: 5747.1264 | D19: =C19*87 -> 500000 | G19: =113300+81799 -> 195099 | J19: =E19*0.27+F19+G19*0.01149+H19+I19 -> 2241.6875 | K19: =C19-J19 -> 3505.4389 | L19: RJPDD/BO/2526/00238 | M19: RJPDD/LPO/2526/00042 | N19: Estimated
A20: 18 | B20: 20” Circulating Head with Leopard connection | C20: 6024.0964 | D20: =C20*87 -> 524096.39 | G20: 420825 | J20: =E20*0.27+F20+G20*0.01149+H20+I20 -> 4835.2793 | K20: =C20-J20 -> 1188.8171 | L20: RJPDD/BO/2526/00113 | M20: RJPDD/LPO/2526/00010 | N20: Estimated
A21: 19 | B21: Procurement of new Cementing Head - 9-5/8" & 13-3/8" | C21: 31927.711 | D21: =C21*87 -> 2777710.8 | G21: 2732850 | J21: =E21*0.27+F21+G21*0.01149+H21+I21 -> 31400.447 | K21: =C21-J21 -> 527.26434 | L21: RJPDD/BO/2526/00112 | M21: RJPDD/LPO/2526/00015 | N21: Estimated
A22: 20 | B22: Additional Capital Expenditure to meet contract requirements | C22: =850000-SUM(C3:C21) -> 298583.1 | D22: =C22*87 -> 25976730 | E22: 16350 | F22: =31000 -> 31000 | G22: =270000+9710960+119969 -> 10100929 | H22: =40435.67+10425+20425 -> 71285.67 | J22: =E22*0.27+F22+G22*0.01149+H22+I22 -> 222759.84 | K22: =C22-J22 -> 75823.257 | L22: RJPDD/BO/2526/00268 RJPDD/BO/2526/00177 RDDPL/BO/2526/00117 RJPDD/BO/2526/00249 RJPSL/BO/2526/00192, RJPSL/BO/2526/00230 RDDPL/BO/2526/00024, RDDPL/BO/2526/00060 | M22: RJPDD/LPO/2526/00062 RJPDD/LPO/2526/00044 RDDPL/IPO/2526/00111 RJPDD/LPO/2526/00028 RJPSL/IPO/2526/00147, RJPSL/IPO/2526/00154 , RDDPL/IPO/2526/00006, RDDPL/IPO/2526/00057 | N22: Ref: JE 2025 contract , including , HAPI lights, CCTV
A23: 21 | B23: Tubulars - drill pipes,heavy weight drill pipes drill collars, pup joints | C23: =1200000 -> 1200000 | D23: =C23*87 -> 104400000 | F23: 6241 | H23: 1059424 | J23: =E23*0.27+F23+G23*0.01149+H23+I23 -> 1065665 | K23: =C23-J23 -> 134335 | L23: RJPSL/BO/2526/00110 RDDPL/BO/2526/00030, RDDPL/BO/2526/00031, RDDPL/BO/2526/00033, RDDPL/BO/2526/00035 | M23: RJPDD/LPO/2526/00028 RJPSL/IPO/2526/00120 RDDPL/IPO/2526/00017, RDDPL/IPO/2526/00044, RDDPL/IPO/2526/00053, RDDPL/IPO/2526/00054 | N23: Currently Pioneer does not have any tubulars
A24: 22 | B24: Fuel & Exhaust gas monitoring system | C24: 35000 | D24: =C24*87 -> 3045000 | G24: 9700000 | J24: =E24*0.27+F24+G24*0.01149+H24+I24 -> 111453 | K24: =C24-J24 -> -76453 | L24: RJPDD/BO/2526/00286 | M24: RJPDD/LPO/2526/00060 | N24: Ref: 2000000lakh + service cost
A25: 23 | B25: Cloud Height Sensor | C25: 35000 | D25: =C25*87 -> 3045000 | J25: =E25*0.27+F25+G25*0.01149+H25+I25 -> 0 | K25: =C25-J25 -> 35000 | N25: Ref: JSUPD D 2023 : USD 32007
A26: 24 | B26: Cementing Unit Procurement | C26: 1500000 | D26: =C26*87 -> 130500000 | H26: =235000+948000 -> 1183000 | J26: =E26*0.27+F26+G26*0.01149+H26+I26 -> 1183000 | K26: =C26-J26 -> 317000 | L26: RDDPL/BO/2526/00043 | M26: RDDPL/IPO/2526/00019 | N26: Ref: Halliburton Quote , including overhauling , New batch mixer & one year operational spares cost
A27: 25 | B27: Start up operational spares | C27: 500000 | D27: =C27*87 -> 43500000 | E27: =9224.5+8550 -> 17774.5 | H27: 22856 | J27: =E27*0.27+F27+G27*0.01149+H27+I27 -> 27655.115 | K27: =C27-J27 -> 472344.89 | L27: RJPSL/BO/2526/00493 RJPSL/BO/2526/00009 RDDPL/BO/2526/00029, RDDPL/BO/2526/00087 | M27: RJPSL/IPO/2526/00353 RJPSL/IPO/2526/00010 RDDPL/IPO/2526/00024, RDDPL/IPO/2526/00108 | N27: Estimated
A28: 26 | B28: DSA, SPOOL,RISERS | C28: 100000 | D28: =C28*87 -> 8700000 | F28: 672 | G28: =2118975.85+6581022 -> 8699997.8 | J28: =E28*0.27+F28+G28*0.01149+H28+I28 -> 100634.98 | K28: =C28-J28 -> -634.9753 | L28: RJPSL/BO/2526/00318 RJPDD/BO/2526/00061 RJPDD/LPO/2526/00017 | M28: RJPSL/IPO/2526/00215 RJPDD/LPO/2526/00016 RJPDD/BO/2526/00062 | N28: Estimated
A29: 27 | B29: Side entry Subs, crossovers,taper mills,cirulcaing subs | C29: 70000 | D29: =C29*87 -> 6090000 | G29: =458640+2111230 -> 2569870 | H29: 33714 | J29: =E29*0.27+F29+G29*0.01149+H29+I29 -> 63241.806 | K29: =C29-J29 -> 6758.1937 | L29: RJPDD/BO/2526/00237 RDDPL/BO/2526/00044 RJPDD/LPO/2526/00012 | M29: RJPDD/LPO/2526/00039 RDDPL/IPO/2526/00011 RJPDD/BO/2526/00057 | N29: Estimated
A30: 28 | B30: Handling tools Procurement of elevator , slips and safety clamps required for contract | C30: 150000 | D30: =C30*87 -> 13050000 | H30: 91477 | J30: =E30*0.27+F30+G30*0.01149+H30+I30 -> 91477 | K30: =C30-J30 -> 58523 | L30: RDDPL/BO/2526/00041, RDDPL/BO/2526/00042 | M30: RDDPL/IPO/2526/00025, RDDPL/IPO/2526/00026 | N30: Estimated
A31: 29 | B31: Cups for cup tester | D31: ='Ann VI-Drill'!F27*87 -> 208800 | H31: 2377 | J31: =E31*0.27+F31+G31*0.01149+H31+I31 -> 2377 | K31: =C31-J31 -> -2377 | L31: RDDPL/BO/2526/00028, | M31: RDDPL/IPO/2526/00007, | N31: Included in Anx VI
A32: 30 | B32: Casing and tubing power tong | C32: 175000 | D32: =C32*87 -> 15225000 | H32: 156000 | J32: =E32*0.27+F32+G32*0.01149+H32+I32 -> 156000 | K32: =C32-J32 -> 19000 | L32: RDDPL/BO/2526/00032 | M32: RDDPL/IPO/2526/00016 | N32: Estimated
A33: 31 | B33: Brine filtration unit filters | C33: 2000 | D33: =C33*87 -> 174000 | G33: 799001 | J33: =E33*0.27+F33+G33*0.01149+H33+I33 -> 9180.5215 | K33: =C33-J33 -> -7180.5215 | L33: RJPDD/BO/2526/00242 | M33: RJPDD/LPO/2526/00036 | N33: Estimated
A34: 32 | B34: High pressure coflex hose 2" 30m | C34: 5000 | D34: =C34*87 -> 435000 | F34: 9685 | J34: =E34*0.27+F34+G34*0.01149+H34+I34 -> 9685 | K34: =C34-J34 -> -4685 | L34: RJPSL/BO/2526/00198 | M34: RJPSL/IPO/2526/00196 | N34: Estimated
A35: 34 | B35: Circulating sub 9 5/8” BTC PIN X 5 ½” FH BOX 13 3/8”BTC PIN X 5 ½” FH BOX | C35: 12000 | D35: =C35*87 -> 1044000 | G35: 450000 | J35: =E35*0.27+F35+G35*0.01149+H35+I35 -> 5170.5 | K35: =C35-J35 -> 6829.5 | L35: RJPDD/BO/2526/00111 | M35: RJPDD/LPO/2526/00022 | N35: Estimated
A36: 35 | B36: Full gauge near bit stabilizer (i)17 ½”, (ii) 12 ¼”, (iii) 8 ½”, (iv) 6” (Box x Pin) | C36: 45000 | D36: =C36*87 -> 3915000 | H36: 24912.36 | J36: =E36*0.27+F36+G36*0.01149+H36+I36 -> 24912.36 | K36: =C36-J36 -> 20087.64 | L36: RDDPL/BO/2526/00046 | M36: RDDPL/IPO/2526/00014 | N36: Quote - TIANHE OIL GROUP
A37: 36 | B37: Under Gauge (1/2") ") integrated type String Stabilizers - 01 each for hole size (Box x Pin) (i) 17 ½”(ii) 12 ¼”,(iii) 8 ½” | D37: =C37*87 -> 0 | J37: =E37*0.27+F37+G37*0.01149+H37+I37 -> 0 | N37: Considered in Sr no 35
A38: 37 | B38: Under Gauge (1/2") ") integrated type String Stabilizers - 01 each for hole size (Box x Box) (i) 17 ½”(ii) 12 ¼”,(iii) 8 ½” | D38: =C38*87 -> 0 | J38: =E38*0.27+F38+G38*0.01149+H38+I38 -> 0 | N38: Considered in Sr no 35
A39: 38 | B39: Under gauge stabilizer Under Gauge (1/4") integrated type String Stabilizers - For 6” hole size (Box x Pin). Under Gauge (1/4") integrated type Near bit Stabilizers -For 6” hole size (Box x Box) Under Gauge (1/8") integrated type String Stabilizers - For 6” hole size (Box x Pin) Under Gauge (1/2") ") integrated type | D39: =C39*87 -> 0 | J39: =E39*0.27+F39+G39*0.01149+H39+I39 -> 0 | N39: Considered in Sr no 35
A40: 39 | B40: Crossover for liner cementing head 5 ½” FH/HT-55 Pin x 4 ½” IF Box -2 Nos each 4 ½” IF Pin x 5 ½” FH/HT-55 Box – 2 Nos each | C40: 10000 | D40: =C40*87 -> 870000 | J40: =E40*0.27+F40+G40*0.01149+H40+I40 -> 0 | K40: =C40-J40 -> 10000 | N40: Estimated
A41: 40 | B41: Coring tools - Outer barrel 6¾” x 4” x 60 ft Core barrel Inner barrel 2 sets : Fibre glass/Aluminum, | C41: 78840 | D41: =C41*87 -> 6859080 | H41: 0 | J41: =E41*0.27+F41+G41*0.01149+H41+I41 -> 0 | K41: =C41-J41 -> 78840 | L41: RDDPL/BO/2526/00049 | M41: RDDPL/IPO/2526/00116 | N41: Estimated
A42: 41 | B42: 7" Shooting nipple | C42: 8000 | D42: =C42*87 -> 696000 | G42: 238300 | J42: =E42*0.27+F42+G42*0.01149+H42+I42 -> 2738.067 | K42: =C42-J42 -> 5261.933 | L42: RJPDD/BO/2526/00173 | M42: RJPDD/LPO/2526/00023 RJPDD/LPO/2526/00024 | N42: Estimated
A43: 42 | B43: Drill cuting storage space (waste skip) | C43: 4000 | D43: =C43*87 -> 348000 | J43: =E43*0.27+F43+G43*0.01149+H43+I43 -> 0 | K43: =C43-J43 -> 4000 | N43: Estimated
A44: 43 | B44: Safety joints | C44: 3000 | D44: =C44*87 -> 261000 | H44: 7994 | J44: =E44*0.27+F44+G44*0.01149+H44+I44 -> 7994 | K44: =C44-J44 -> -4994 | L44: RDDPL/BO/2526/00038 | M44: RDDPL/IPO/2526/00012 | N44: Estimated
A45: 44 | B45: Dicth Magnet - 2NOS | C45: 4000 | D45: =C45*87 -> 348000 | H45: 5328 | J45: =E45*0.27+F45+G45*0.01149+H45+I45 -> 5328 | K45: =C45-J45 -> -1328 | L45: RDDPL/BO/2526/00039 | M45: RDDPL/IPO/2526/00013 | N45: Estimated
A46: 45 | B46: Impression blocks | C46: 20000 | D46: =C46*87 -> 1740000 | H46: 15184 | J46: =E46*0.27+F46+G46*0.01149+H46+I46 -> 15184 | K46: =C46-J46 -> 4816 | L46: RDDPL/BO/2526/00037 | M46: RDDPL/IPO/2526/00010 | N46: Estimated
A47: 46 | B47: Hole openers 23'' , 26'' | C47: 100000 | D47: =C47*87 -> 8700000 | H47: 104470 | J47: =E47*0.27+F47+G47*0.01149+H47+I47 -> 104470 | K47: =C47-J47 -> -4470 | L47: RDDPL/BO/2526/00040 | M47: RDDPL/IPO/2526/00028 | N47: Estimated
A48: 47 | B48: Water maker | C48: 40000 | D48: =C48*87 -> 3480000 | H48: 44998.31 | J48: =E48*0.27+F48+G48*0.01149+H48+I48 -> 44998.31 | K48: =C48-J48 -> -4998.31 | L48: RDDPL/BO/2526/00081 | M48: RDDPL/IPO/2526/00021 | N48: Estimated
A49: Total | C49: =SUM(C3:C48) -> 4946840 | D49: =SUM(D3:D48) -> 430583880 | I49: =SUM(I3:I48) -> 0 | J49: =SUM(J3:J48) -> 3498986.6 | K49: =C49-J49 -> 1447853.4
A51: NOTE: 1) Additional 5 % VAT may be applicable to all line items depending on location of purchase. 2) Towing charges from UAE to Mumbai not considered as it is part of ONGC mobilisation cost

Sheet Ann XI-Missing items Saipem
A1: Missing items from rig Jindal Pioneer -post handover from Saipem
A2: S.No | B2: Equipment Description | C2: Budgetary Cost Total in USD | D2: Budgetary Cost Total in INR | E2: Total in INR | F2: Actual Cost local | G2: Actual Cost Import | H2: Actucal Total Cost (USD) | I2: Surplus/Exceeded | J2: MR NO | K2: PO NO | L2: Remarks
A3: 1 | B3: Handling equipment | C3: 130000 | D3: =C3*87 -> 11310000 | E3: 197960 | F3: =6928+1675+2117+1048+4345+43500+1040+2342+3842+1202.71+1855+1820+1748+539+2295+579+2619 -> 79494.71 | H3: =E3*0.01149+F3*0.27+G3 -> 23738.132 | I3: =C3-H3 -> 106261.87 | J3: RJPSL/BO/2526/00343 RJPSL/BO/2526/00408, RJPSL/BO/2526/00409 RJPSL/BO/2526/00423 RJPSL/BO/2526/00429, RJPSL/BO/2526/00371, RJPSL/BO/2526/00376 RJPSL/BO/2526/00418 RJPDD/BO/2526/00272 RJPSL/BO/2526/00407, RJPSL/BO/2526/00456, RJPSL/BO/2526/00430 RJPSL/BO/2526/00386 RJPSL/BO/2526/00342 RJPSL/BO/2526/00339 RJPSL/BO/2526/00387 RJPSL/BO/2526/00351 RJPSL/BO/2526/00399 | K3: RJPSL/IPO/2627/00011 RJPSL/IPO/2627/00008, RJPSL/IPO/2627/00009 RJPSL/IPO/2526/00356 RJPSL/IPO/2526/00336, RJPSL/IPO/2526/00341, RJPSL/IPO/2526/00345 RJPSL/IPO/2526/00331 RJPDD/LPO/2526/00053 RJPSL/IPO/2526/00322, RJPSL/IPO/2526/00323, RJPSL/IPO/2526/00319 RJPSL/IPO/2526/00289 RJPSL/IPO/2526/00275 RJPSL/IPO/2526/00269 RJPSL/IPO/2526/00267 RJPSL/IPO/2526/00244 RJPSL/IPO/2526/00272 | L3: Estimated
A4: 2 | B4: Fishing tools | C4: 65050 | D4: =C4*87 -> 5659350 | G4: =15345+5053 -> 20398 | H4: =E4*0.01149+F4*0.27+G4 -> 20398 | I4: =C4-H4 -> 44652 | J4: RDDPL/BO/2526/00177 RDDPL/BO/2526/00093 | K4: RDDPL/IPO/2526/00149 RDDPL/IPO/2526/00099 | L4: Quote- EOSS
A5: 3 | B5: TDS- encoder | C5: 10000 | D5: =C5*87 -> 870000 | H5: =E5*0.01149+F5*0.27+G5 -> 0 | I5: =C5-H5 -> 10000 | L5: Quote
A6: 4 | B6: Ex telephones | C6: 10000 | D6: =C6*87 -> 870000 | H6: =E6*0.01149+F6*0.27+G6 -> 0 | I6: =C6-H6 -> 10000 | L6: Estimated
A7: 5 | B7: Work vests | C7: 2000 | D7: =C7*87 -> 174000 | H7: =E7*0.01149+F7*0.27+G7 -> 0 | I7: =C7-H7 -> 2000 | L7: Estimated
A8: 6 | B8: STP- Aeration blower | C8: 10000 | D8: =C8*87 -> 870000 | H8: =E8*0.01149+F8*0.27+G8 -> 0 | I8: =C8-H8 -> 10000 | L8: Estimated for One aeration blower missing
A9: 7 | B9: FOSV Procuremnt of (4-1/2"IF, 5-1/2FH") | C9: =12250-3500 -> 8750 | D9: =C9*87 -> 761250 | H9: =E9*0.01149+F9*0.27+G9 -> 0 | I9: =C9-H9 -> 8750 | J9: 0 | L9: Quote- Packard International. Value for Qty-1 (5-1/2) and Qty -1 (4-1/2IF)
A10: 8 | B10: Elevator links 2 -3/4" x 144" 350 TONS | C10: 10000 | D10: =C10*87 -> 870000 | G10: =19740.69+616 -> 20356.69 | H10: =E10*0.01149+F10*0.27+G10 -> 20356.69 | I10: =C10-H10 -> -10356.69 | J10: RDDPL/BO/2526/00124 | K10: RDDPL/IPO/2526/00093 | L10: Estimated
A11: 9 | B11: Missing radio room equipments | C11: 5000 | D11: =C11*87 -> 435000 | H11: =E11*0.01149+F11*0.27+G11 -> 0 | I11: =C11-H11 -> 5000 | L11: Aeronautical vhf transceiver
A12: 10 | B12: Grinder machine | C12: 3000 | D12: =C12*87 -> 261000 | H12: =E12*0.01149+F12*0.27+G12 -> 0 | I12: =C12-H12 -> 3000 | L12: Estimated
A13: 11 | B13: Vice | C13: 850 | D13: =C13*87 -> 73950 | H13: =E13*0.01149+F13*0.27+G13 -> 0 | I13: =C13-H13 -> 850 | L13: Estimated
A14: 12 | B14: H2S and Gas Detectors | C14: 2500 | D14: =C14*87 -> 217500 | H14: =E14*0.01149+F14*0.27+G14 -> 0 | I14: =C14-H14 -> 2500 | L14: Estimated
A15: 13 | B15: Nozzles | C15: 10000 | D15: =C15*87 -> 870000 | H15: =E15*0.01149+F15*0.27+G15 -> 0 | I15: =C15-H15 -> 10000
A16: 14 | B16: Engine overhaul cost | C16: 500000 | D16: =C16*87 -> 43500000 | G16: 206398.98 | H16: =E16*0.01149+F16*0.27+G16 -> 206398.98 | I16: =C16-H16 -> 293601.02 | J16: RDDPL/BO/2526/00097 | K16: RDDPL/IPO/2526/00098 | L16: Reference Anx VII-sl no.1
A17: 15 | B17: Water heater | C17: 25000 | D17: =C17*87 -> 2175000 | H17: =E17*0.01149+F17*0.27+G17 -> 0 | I17: =C17-H17 -> 25000
A18: 16 | B18: Bench vise | C18: 5000 | D18: =C18*87 -> 435000 | H18: =E18*0.01149+F18*0.27+G18 -> 0 | I18: =C18-H18 -> 5000
A19: 17 | B19: Fuel centrifuge main motor | C19: 19850 | D19: =C19*87 -> 1726950 | H19: =E19*0.01149+F19*0.27+G19 -> 0 | I19: =C19-H19 -> 19850
B20: Total | C20: =SUM(C3:C14) -> 257150 | D20: =C20*87 -> 22372050 | H20: =SUM(H3:H14) -> 64492.822 | I20: =C20-H20 -> 192657.18
B23: Note: The items highlighted in yellow above were not included in the approved budget. These requirements were confirmed and finalized during the final meeting with Saipem prior to handover. The total amount for these additional items is USD 554,850, which includes: 1.Engine TOH spares cost for 3 engines and Service cost for 4 engines 2.Nozzles 3.Water heater 4.Bench vise 5.Fuel centrifuge main motors
